{"connect":{"statusCode":200,"response":{"id":"","name":"BTC Trade UA","private":false,"enableRateLimit":true,"countries":["UA"],"rateLimit":3000,"has":{"loadMarkets":"true","cancelAllOrders":"false","cancelOrder":"true","cancelOrders":"false","CORS":"false","createDepositAddress":"false","createLimitOrder":"true","createMarketOrder":"false","createOrder":"true","deposit":"false","editOrder":"emulated","fetchBalance":"true","fetchBidsAsks":"false","fetchClosedOrders":"false","fetchCurrencies":"false","fetchDepositAddress":"false","fetchDeposits":"false","fetchFundingFees":"false","fetchL2OrderBook":"true","fetchLedger":"false","fetchMarkets":"true","fetchMyTrades":"false","fetchOHLCV":"emulated","fetchOpenOrders":"true","fetchOrder":"false","fetchOrderBook":"true","fetchOrderBooks":"false","fetchOrders":"false","fetchOrderTrades":"false","fetchStatus":"emulated","fetchTicker":"true","fetchTickers":"false","fetchTime":"false","fetchTrades":"true","fetchTradingFee":"false","fetchTradingFees":"false","fetchTradingLimits":"false","fetchTransactions":"false","fetchWithdrawals":"false","privateAPI":"true","publicAPI":"true","withdraw":"false","signIn":"true"},"urls":{"logo":"https://user-images.githubusercontent.com/1294454/27941483-79fc7350-62d9-11e7-9f61-ac47f28fcd96.jpg","api":"https://btc-trade.com.ua/api","www":"https://btc-trade.com.ua","doc":"https://docs.google.com/document/d/1ocYA0yMy_RXd561sfG3qEPZ80kyll36HUxvCRe5GbhE/edit","referral":"https://btc-trade.com.ua/registration/22689"}}},"markets":{"statusCode":200,"response":[{"id":"bch_uah","symbol":"BCH/UAH","base":"BCH","quote":"UAH","limits":{"amount":{},"price":{},"cost":{}},"precision":{}},{"id":"btc_uah","symbol":"BTC/UAH","base":"BTC","quote":"UAH","limits":{"amount":{"min":1e-10},"price":{},"cost":{}},"precision":{"price":1}},{"id":"dash_btc","symbol":"DASH/BTC","base":"DASH","quote":"BTC","limits":{"amount":{},"price":{},"cost":{}},"precision":{}},{"id":"dash_uah","symbol":"DASH/UAH","base":"DASH","quote":"UAH","limits":{"amount":{},"price":{},"cost":{}},"precision":{}},{"id":"doge_btc","symbol":"DOGE/BTC","base":"DOGE","quote":"BTC","limits":{"amount":{},"price":{},"cost":{}},"precision":{}},{"id":"doge_uah","symbol":"DOGE/UAH","base":"DOGE","quote":"UAH","limits":{"amount":{},"price":{},"cost":{}},"precision":{}},{"id":"eth_uah","symbol":"ETH/UAH","base":"ETH","quote":"UAH","limits":{"amount":{},"price":{},"cost":{}},"precision":{}},{"id":"iti_uah","symbol":"ITI/UAH","base":"ITI","quote":"UAH","limits":{"amount":{},"price":{},"cost":{}},"precision":{}},{"id":"krb_uah","symbol":"KRB/UAH","base":"KRB","quote":"UAH","limits":{"amount":{},"price":{},"cost":{}},"precision":{}},{"id":"ltc_btc","symbol":"LTC/BTC","base":"LTC","quote":"BTC","limits":{"amount":{},"price":{},"cost":{}},"precision":{}},{"id":"ltc_uah","symbol":"LTC/UAH","base":"LTC","quote":"UAH","limits":{"amount":{},"price":{},"cost":{}},"precision":{}},{"id":"nvc_btc","symbol":"NVC/BTC","base":"NVC","quote":"BTC","limits":{"amount":{},"price":{},"cost":{}},"precision":{}},{"id":"nvc_uah","symbol":"NVC/UAH","base":"NVC","quote":"UAH","limits":{"amount":{},"price":{},"cost":{}},"precision":{}},{"id":"ppc_btc","symbol":"PPC/BTC","base":"PPC","quote":"BTC","limits":{"amount":{},"price":{},"cost":{}},"precision":{}},{"id":"sib_uah","symbol":"SIB/UAH","base":"SIB","quote":"UAH","limits":{"amount":{},"price":{},"cost":{}},"precision":{}},{"id":"xmr_uah","symbol":"XMR/UAH","base":"XMR","quote":"UAH","limits":{"amount":{},"price":{},"cost":{}},"precision":{}},{"id":"zec_uah","symbol":"ZEC/UAH","base":"ZEC","quote":"UAH","limits":{"amount":{},"price":{},"cost":{}},"precision":{}}]},"ticker":{"statusCode":200,"response":{"symbol":"BCH/UAH","timestamp":1619541758426,"datetime":"2021-04-27T16:42:38.426Z","high":24444.999,"low":24398,"close":24444.999,"last":24444.999,"baseVolume":0.652379,"info":[[1616961871000,14099,14099,14099,14099,0],[1616963672000,14099,14099,14099,14099,0],[1616965473000,14099,14099,14099,14099,0],[1616967274000,14099,14099,14099,14099,0],[1616969075000,14099,14099,14099,14099,0],[1616970876000,14099,14099,14099,14099,0],[1616972677000,14099,14099,14099,14099,0],[1616974478000,14099,14099,14099,14099,0],[1616976279000,14099,14099,14099,14099,0],[1616978080000,14099,14099,14099,14099,0],[1616979881000,14099,14099,14099,14099,0],[1616981682000,14099,14099,14099,14099,0],[1616983483000,14099,14099,14099,14099,0],[1616985284000,14099,14099,14099,14099,0],[1616987085000,14099,14099,14099,14099,0],[1616988886000,14099,14099,14099,14099,0],[1616990687000,14099,14099,14099,14099,0],[1616992488000,14099,14099,14099,14099,0],[1616994289000,14099,14099,14099,14099,0],[1616996090000,14099,14099,14099,14099,0],[1616997891000,14099,14099,14099,14099,0],[1616999692000,14099,14099,14099,14099,0],[1617001493000,14099,14099,14099,14099,0],[1617003294000,14099,14099,14099,14099,0],[1617005095000,14099,14099,14099,14099,0],[1617006896000,14099,14099,14099,14099,0],[1617008697000,14099,14099,14099,14099,0],[1617010498000,14099,14099,14099,14099,0],[1617012299000,14099,14099,14099,14099,0],[1617014100000,14099,14099,14099,14099,0],[1617015901000,14099,14099,14099,14099,0],[1617017702000,14099,14099,14099,14099,0],[1617019503000,14099,14099,14099,14099,0],[1617021304000,14099,13889.186407,13889.186407,13889.186407,0.041731],[1617023105000,13889.186407,13889.186407,13889.186407,13889.186407,0],[1617024906000,13889.186407,13889.186407,13889.186407,13889.186407,0],[1617026707000,13889.186407,13889.186407,13889.186407,13889.186407,0],[1617028508000,13889.186407,14099,14099,14099,0.01612],[1617030309000,14099,14010,14010,14010,0.038512],[1617032110000,14010,14010,14010,14010,0],[1617033911000,14010,14010,14010,14010,0],[1617035712000,14010,14010,14010,14010,0],[1617037513000,14010,14010,14010,14010,0],[1617039314000,14010,14010,14010,14010,0],[1617041115000,14010,14010,14010,14010,0],[1617042916000,14010,14010,14010,14010,0],[1617044717000,14010,14010,14010,14010,0],[1617046518000,14010,14010,14010,14010,0],[1617048319000,14010,14010,14010,14010,0],[1617050120000,14010,14514.000001,14495,14514.000001,0.382157],[1617051921000,14514.000001,14514.000001,14514.000001,14514.000001,0],[1617053722000,14514.000001,14514.000001,14514.000001,14514.000001,0],[1617055523000,14514.000001,14514.000001,14514.000001,14514.000001,0],[1617057324000,14514.000001,14514.000001,14514.000001,14514.000001,0],[1617059125000,14514.000001,14884.557721,14884.557721,14884.557721,0.014512],[1617060926000,14884.557721,14884.557721,14884.557721,14884.557721,0],[1617062727000,14884.557721,14884.557721,14884.557721,14884.557721,0],[1617064528000,14884.557721,14884.557721,14884.557721,14884.557721,0],[1617066329000,14884.557721,14884.557721,14884.557721,14884.557721,0],[1617068130000,14884.557721,14884.557721,14884.557721,14884.557721,0],[1617069931000,14884.557721,14884.557721,14884.557721,14884.557721,0],[1617071732000,14884.557721,14884.557721,14884.557721,14884.557721,0],[1617073533000,14884.557721,14884.557721,14884.557721,14884.557721,0],[1617075334000,14884.557721,14884.557721,14884.557721,14884.557721,0],[1617077135000,14884.557721,14068.132551,14068.132551,14068.132551,0.007554],[1617078936000,14068.132551,14068.132551,14068.132551,14068.132551,0],[1617080737000,14068.132551,14068.132551,14068.132551,14068.132551,0],[1617082538000,14068.132551,14068.132551,14068.132551,14068.132551,0],[1617084339000,14068.132551,14068.132551,14068.132551,14068.132551,0],[1617086140000,14068.132551,14068.132551,14068.132551,14068.132551,0],[1617087941000,14068.132551,14068.132551,14068.132551,14068.132551,0],[1617089742000,14068.132551,14068.132551,14068.132551,14068.132551,0],[1617091543000,14068.132551,14068.132551,14068.132551,14068.132551,0],[1617093344000,14068.132551,14068.132551,14068.132551,14068.132551,0],[1617095145000,14068.132551,14068.132551,14068.132551,14068.132551,0],[1617096946000,14068.132551,14068.132551,14068.132551,14068.132551,0],[1617098747000,14068.132551,14068.132551,14068.132551,14068.132551,0],[1617100548000,14068.132551,14068.132551,14068.132551,14068.132551,0],[1617102349000,14068.132551,14068.132551,14068.132551,14068.132551,0],[1617104150000,14068.132551,14068.132551,14068.132551,14068.132551,0],[1617105951000,14068.132551,14068.132551,14068.132551,14068.132551,0],[1617107752000,14068.132551,14068.132551,14068.132551,14068.132551,0],[1617109553000,14068.132551,14068.132551,14068.132551,14068.132551,0],[1617111354000,14068.132551,14068.132551,14068.132551,14068.132551,0],[1617113155000,14068.132551,14614.603646,14590.000007,14590.000007,0.381966],[1617114956000,14590.000007,14500,14500,14500,0.15],[1617116757000,14500,14500,14500,14500,0],[1617118558000,14500,14500,14500,14500,0],[1617120359000,14500,14500,14500,14500,0.15],[1617122160000,14500,14151.798488,14011,14011,0.296326],[1617123961000,14011,14011.001,14011.001,14011.001,0.055102],[1617125762000,14011.001,14011.001,14011.001,14011.001,0],[1617127563000,14011.001,14011.001,14011.001,14011.001,0],[1617129364000,14011.001,14011.001,14011.001,14011.001,0],[1617131165000,14011.001,14011.001,14011.001,14011.001,0],[1617132966000,14011.001,14011.001,14011.001,14011.001,0],[1617134767000,14011.001,14011.001,14011.001,14011.001,0],[1617136568000,14011.001,14011.001,14011.001,14011.001,0],[1617138369000,14011.001,14550,14550,14550,0.100811],[1617140170000,14550,14550,14550,14550,0],[1617141971000,14550,14550,14550,14550,0],[1617143772000,14550,14550,14550,14550,0],[1617145573000,14550,14550,14550,14550,0],[1617147374000,14550,14550,14550,14550,0],[1617149175000,14550,14550,14550,14550,0],[1617150976000,14550,14550,14550,14550,0],[1617152777000,14550,14550,14550,14550,0],[1617154578000,14550,14550,14550,14550,0],[1617156379000,14550,14550,14550,14550,0],[1617158180000,14550,14550,14550,14550,0],[1617159981000,14550,14550,14550,14550,0],[1617161782000,14550,14550,14550,14550,0],[1617163583000,14550,14550,14550,14550,0],[1617165384000,14550,14550,14550,14550,0],[1617167185000,14550,14550,14550,14550,0],[1617168986000,14550,14550,14550,14550,0],[1617170787000,14550,14550,14550,14550,0],[1617172588000,14550,14550,14550,14550,0],[1617174389000,14550,14550,14550,14550,0],[1617176190000,14550,14550,14550,14550,0],[1617177991000,14550,14550,14550,14550,0],[1617179792000,14550,14550,14550,14550,0],[1617181593000,14550,14550,14550,14550,0],[1617183394000,14550,14550,14550,14550,0],[1617185195000,14550,14550,14550,14550,0],[1617186996000,14550,14550,14550,14550,0],[1617188797000,14550,14010,14000,14000,0.032916],[1617190598000,14000,14000,13335.093843,13335.093843,0.3464],[1617192399000,13335.093843,13335.093843,13335.093843,13335.093843,0],[1617194200000,13335.093843,13335.093843,13335.093843,13335.093843,0],[1617196001000,13335.093843,14518.752623,14518.752623,14518.752623,0.05],[1617197802000,14518.752623,14518.752623,14518.752623,14518.752623,0],[1617199603000,14518.752623,14518.752623,14518.752623,14518.752623,0],[1617201404000,14518.752623,14518.752623,14518.752623,14518.752623,0],[1617203205000,14518.752623,14518.752623,14518.752623,14518.752623,0],[1617205006000,14518.752623,13620.410202,13620.410202,13620.410202,0.049899],[1617206807000,13620.410202,13606.8,13505.93398,13505.93398,0.361019],[1617208608000,13505.93398,13505.93398,13505.93398,13505.93398,0],[1617210409000,13505.93398,13505.93398,13505.93398,13505.93398,0],[1617212210000,13505.93398,13505.93398,13505.93398,13505.93398,0],[1617214011000,13505.93398,14114.103525,14114.103525,14114.103525,0.001499],[1617215812000,14114.103525,14200,14150,14150,0.1999],[1617217613000,14150,14150,14150,14150,0],[1617219414000,14150,14150,14150,14150,0],[1617221215000,14150,14150,14150,14150,0],[1617223016000,14150,14150,14150,14150,0],[1617224817000,14150,14150,14150,14150,0],[1617226618000,14150,14150,14150,14150,0],[1617228419000,14150,14150,14150,14150,0],[1617230220000,14150,14150,14150,14150,0],[1617232021000,14150,14150,14150,14150,0],[1617233822000,14150,14150,14150,14150,0],[1617235623000,14150,14150,14150,14150,0],[1617237424000,14150,14884.558026,14514,14884.558026,0.322171],[1617239225000,14884.558026,14884.558026,14884.558026,14884.558026,0],[1617241026000,14884.558026,14884.558026,14884.558026,14884.558026,0],[1617242827000,14884.558026,14884.558026,14884.558026,14884.558026,0],[1617244628000,14884.558026,14884.558026,14884.558026,14884.558026,0],[1617246429000,14884.558026,14884.558026,14884.558026,14884.558026,0],[1617248230000,14884.558026,14884.558026,14884.558026,14884.558026,0],[1617250031000,14884.558026,14884.558026,14884.558026,14884.558026,0],[1617251832000,14884.558026,14884.558026,14884.558026,14884.558026,0],[1617253633000,14884.558026,14884.558026,14884.558026,14884.558026,0],[1617255434000,14884.558026,14884.558026,14884.558026,14884.558026,0],[1617257235000,14884.558026,14884.558026,14884.558026,14884.558026,0],[1617259036000,14884.558026,14884.558026,14884.558026,14884.558026,0],[1617260837000,14884.558026,14884.558026,14884.558026,14884.558026,0],[1617262638000,14884.558026,14884.558026,14884.558026,14884.558026,0],[1617264439000,14884.558026,14884.558026,14884.558026,14884.558026,0],[1617266240000,14884.558026,14884.558026,14884.558026,14884.558026,0],[1617268041000,14884.558026,14884.558026,14884.558026,14884.558026,0],[1617269842000,14884.558026,14884.558026,14884.558026,14884.558026,0],[1617271643000,14884.558026,14884.558026,14884.558026,14884.558026,0],[1617273444000,14884.558026,14884.558026,14884.558026,14884.558026,0],[1617275245000,14884.558026,14884.558026,14884.558026,14884.558026,0],[1617277046000,14884.558026,14884.558026,14884.558026,14884.558026,0],[1617278847000,14884.558026,14884.558026,14884.558026,14884.558026,0],[1617280648000,14884.558026,14884.558026,14884.558026,14884.558026,0],[1617282449000,14884.558026,14884.558026,14884.558026,14884.558026,0],[1617284250000,14884.558026,14884.558026,14884.558026,14884.558026,0],[1617286051000,14884.558026,14884.558026,14884.558026,14884.558026,0],[1617287852000,14884.558026,14700,14700,14700,1.99999],[1617289653000,14700,14700,14700,14700,0],[1617291454000,14700,14700,14700,14700,0],[1617293255000,14700,14700,14700,14700,0],[1617295056000,14700,14700,14700,14700,0],[1617296857000,14700,14700,14700,14700,0],[1617298658000,14700,14700,14700,14700,0],[1617300459000,14700,14700,14700,14700,0],[1617302260000,14700,14700,14700,14700,0],[1617304061000,14700,14884.558,14884.558,14884.558,0.009995],[1617305862000,14884.558,14884.558,14884.558,14884.558,0],[1617307663000,14884.558,14884.558,14884.558,14884.558,0],[1617309464000,14884.558,14050.966941,14050.966941,14050.966941,0.010135],[1617311265000,14050.966941,14050.966941,14050.966941,14050.966941,0],[1617313066000,14050.966941,14050.966941,14050.966941,14050.966941,0],[1617314867000,14050.966941,14050.966941,14050.966941,14050.966941,0],[1617316668000,14050.966941,14800,14800,14800,0.02434],[1617318469000,14800,14800,14800,14800,0],[1617320270000,14800,14800,14800,14800,0],[1617322071000,14800,14800,14800,14800,0],[1617323872000,14800,14800,14800,14800,0],[1617325673000,14800,14800,14800,14800,0],[1617327474000,14800,14800,14800,14800,0],[1617329275000,14800,14800,14800,14800,0],[1617331076000,14800,14800,14800,14800,0],[1617332877000,14800,14800,14800,14800,0],[1617334678000,14800,14800,14800,14800,0],[1617336479000,14800,14800,14800,14800,0],[1617338280000,14800,15000,15000,15000,0.1046],[1617340081000,15000,15000,15000,15000,0],[1617341882000,15000,15000,15000,15000,0],[1617343683000,15000,15000,15000,15000,0],[1617345484000,15000,15000,15000,15000,0],[1617347285000,15000,15000,15000,15000,0],[1617349086000,15000,15000,15000,15000,0],[1617350887000,15000,15000,15000,15000,0],[1617352688000,15000,15000,15000,15000,0],[1617354489000,15000,15000,15000,15000,0],[1617356290000,15000,15000,15000,15000,0],[1617358091000,15000,15000,15000,15000,0],[1617359892000,15000,15000,15000,15000,0],[1617361693000,15000,15000,15000,15000,0],[1617363494000,15000,15000,15000,15000,0],[1617365295000,15000,15000.000003,15000,15000.000003,0.0794],[1617367096000,15000.000003,15015,15015,15015,0.018691],[1617368897000,15015,15015,15015,15015,0],[1617370698000,15015,15015,15015,15015,0],[1617372499000,15015,15015,15015,15015,0],[1617374300000,15015,15515,15515,15515,0.018025],[1617376101000,15515,15515,15515,15515,0],[1617377902000,15515,15515,15515,15515,0],[1617379703000,15515,15515,15515,15515,0],[1617381504000,15515,15515,15515,15515,0],[1617383305000,15515,15515,15515,15515,0],[1617385106000,15515,15515,15515,15515,0],[1617386907000,15515,15515,15515,15515,0],[1617388708000,15515,15550,15550,15550,0.1999],[1617390509000,15550,16495.000007,15600.005499,16495.000007,0.945232],[1617392310000,16495.000007,16495,16495,16495,0.072749],[1617394111000,16495,16495,16495,16495,0],[1617395912000,16495,16495,16495,16495,0],[1617397713000,16495,16495,16495,16495,0],[1617399514000,16495,16495,16495,16495,0],[1617401315000,16495,16495,16495,16495,0],[1617403116000,16495,16495,16495,16495,0],[1617404917000,16495,16495,16495,16495,0],[1617406718000,16495,16495,16495,16495,0],[1617408519000,16495,16495,16495,16495,0],[1617410320000,16495,16495,16495,16495,0],[1617412121000,16495,16495,16495,16495,0],[1617413922000,16495,16495,16495,16495,0],[1617415723000,16495,16495,16495,16495,0],[1617417524000,16495,16495,16495,16495,0],[1617419325000,16495,16495,16495,16495,0],[1617421126000,16495,16495,16495,16495,0],[1617422927000,16495,16495,16495,16495,0],[1617424728000,16495,16495,16495,16495,0],[1617426529000,16495,16495,16495,16495,0],[1617428330000,16495,16495,16495,16495,0],[1617430131000,16495,16495,16495,16495,0],[1617431932000,16495,16495,16495,16495,0],[1617433733000,16495,16495,16495,16495,0],[1617435534000,16495,16495,16495,16495,0],[1617437335000,16495,16495,16495,16495,0],[1617439136000,16495,16495,16495,16495,0],[1617440937000,16495,16495,16495,16495,0],[1617442738000,16495,16495,16495,16495,0],[1617444539000,16495,16495,16495,16495,0],[1617446340000,16495,16495,16495,16495,0],[1617448141000,16495,16495,16495,16495,0],[1617449942000,16495,16495,16495,16495,0],[1617451743000,16495,15605,15605,15605,0.010143],[1617453544000,15605,15605,15605,15605,0],[1617455345000,15605,15605,15605,15605,0],[1617457146000,15605,15605,15605,15605,0],[1617458947000,15605,15605,15605,15605,0],[1617460748000,15605,15605,15605,15605,0],[1617462549000,15605,15605,15605,15605,0],[1617464350000,15605,15605,15605,15605,0],[1617466151000,15605,15605,15605,15605,0],[1617467952000,15605,15605,15605,15605,0],[1617469753000,15605,15605,15605,15605,0],[1617471554000,15605,15605,15605,15605,0],[1617473355000,15605,15605,15605,15605,0],[1617475156000,15605,15605,15605,15605,0.006451],[1617476957000,15605,15605,15605,15605,0],[1617478758000,15605,15605,15605,15605,0],[1617480559000,15605,15605,15605,15605,0.001405],[1617482360000,15605,15155,15020.000001,15020.000001,0.4486],[1617484161000,15020.000001,15020.000001,15020.000001,15020.000001,0],[1617485962000,15020.000001,15020.000001,15020.000001,15020.000001,0],[1617487763000,15020.000001,15020.000001,15020.000001,15020.000001,0],[1617489564000,15020.000001,15020.000001,15020.000001,15020.000001,0],[1617491365000,15020.000001,15020.000001,15020.000001,15020.000001,0],[1617493166000,15020.000001,15020.000001,15020.000001,15020.000001,0],[1617494967000,15020.000001,15020.000001,15020.000001,15020.000001,0],[1617496768000,15020.000001,15018.010026,15018.010026,15018.010026,0.009987],[1617498569000,15018.010026,15018.010026,15018.010026,15018.010026,0],[1617500370000,15018.010026,15018.010026,15018.010026,15018.010026,0],[1617502171000,15018.010026,15018.010026,15018.010026,15018.010026,0],[1617503972000,15018.010026,15018.010026,15018.010026,15018.010026,0],[1617505773000,15018.010026,15018.010026,15018.010026,15018.010026,0],[1617507574000,15018.010026,15018.010026,15018.010026,15018.010026,0],[1617509375000,15018.010026,15018.010026,15018.010026,15018.010026,0],[1617511176000,15018.010026,15018.010026,15018.010026,15018.010026,0],[1617512977000,15018.010026,15018.010026,15018.010026,15018.010026,0],[1617514778000,15018.010026,15018.010026,15018.010026,15018.010026,0],[1617516579000,15018.010026,15018.010026,15018.010026,15018.010026,0],[1617518380000,15018.010026,15018.010026,15018.010026,15018.010026,0],[1617520181000,15018.010026,15018.010026,15018.010026,15018.010026,0],[1617521982000,15018.010026,15018.010026,15018.010026,15018.010026,0],[1617523783000,15018.010026,15018.010026,15018.010026,15018.010026,0],[1617525584000,15018.010026,15018.010026,15018.010026,15018.010026,0],[1617527385000,15018.010026,15018.010026,15018.010026,15018.010026,0],[1617529186000,15018.010026,15018.010026,15018.010026,15018.010026,0],[1617530987000,15018.010026,15018.010026,15018.010026,15018.010026,0],[1617532788000,15018.010026,15640.999,15500,15640.999,0.011667],[1617534589000,15640.999,15640.999,15640.999,15640.999,0],[1617536390000,15640.999,14571,14571,14571,0.018143],[1617538191000,14571,14571,14571,14571,0],[1617539992000,14571,14571,14571,14571,0],[1617541793000,14571,14571,14571,14571,0],[1617543594000,14571,14571,14571,14571,0],[1617545395000,14571,14571,14571,14571,0],[1617547196000,14571,14571,14571,14571,0],[1617548997000,14571,14571,14571,14571,0],[1617550798000,14571,14571,14571,14571,0],[1617552599000,14571,14571,14571,14571,0],[1617554400000,14571,14571,14571,14571,0],[1617556201000,14571,14571,14571,14571,0],[1617558002000,14571,14571,14571,14571,0],[1617559803000,14571,14571,14571,14571,0],[1617561604000,14571,14571,14571,14571,0],[1617563405000,14571,14571,14571,14571,0],[1617565206000,14571,14571,14571,14571,0],[1617567007000,14571,14571,14571,14571,0],[1617568808000,14571,14571,14571,14571,0],[1617570609000,14571,14571,14571,14571,0],[1617572410000,14571,14571,14571,14571,0],[1617574211000,14571,14571,14571,14571,0],[1617576012000,14571,14571,14571,14571,0],[1617577813000,14571,14571,14571,14571,0],[1617579614000,14571,14571,14571,14571,0],[1617581415000,14571,14571,14571,14571,0],[1617583216000,14571,14571,14571,14571,0],[1617585017000,14571,14571,14571,14571,0],[1617586818000,14571,14571,14571,14571,0],[1617588619000,14571,14571,14571,14571,0],[1617590420000,14571,14571,14571,14571,0],[1617592221000,14571,14571,14571,14571,0],[1617594022000,14571,14571,14571,14571,0],[1617595823000,14571,14571,14571,14571,0],[1617597624000,14571,14571,14571,14571,0],[1617599425000,14571,15640,15640,15640,0.018988],[1617601226000,15640,15815,15640,15815,1.80459],[1617603027000,15815,15815,15815,15815,0],[1617604828000,15815,15815,15815,15815,0],[1617606629000,15815,15815,15815,15815,0],[1617608430000,15815,15815,15815,15815,0],[1617610231000,15815,15819.745,15819.745,15819.745,0.006538],[1617612032000,15819.745,15819.745,15819.745,15819.745,0],[1617613833000,15819.745,15819.745,15819.745,15819.745,0],[1617615634000,15819.745,15819.745,15819.745,15819.745,0],[1617617435000,15819.745,15819.745,15819.745,15819.745,0],[1617619236000,15819.745,15819.745,15819.745,15819.745,0],[1617621037000,15819.745,15819.745,15819.745,15819.745,0],[1617622838000,15819.745,16150,14852.521076,14852.521076,0.206],[1617624639000,14852.521076,14852.521076,14852.521076,14852.521076,0],[1617626440000,14852.521076,14852.521076,14852.521076,14852.521076,0],[1617628241000,14852.521076,14852.521076,14852.521076,14852.521076,0],[1617630042000,14852.521076,14852.521076,14852.521076,14852.521076,0],[1617631843000,14852.521076,16512.00003,16126.624996,16512.00003,0.495605],[1617633644000,16512.00003,16512.00003,16512.00003,16512.00003,0],[1617635445000,16512.00003,16511.99999,16511.99999,16511.99999,0.074388],[1617637246000,16511.99999,16511.99999,16511.99999,16511.99999,0],[1617639047000,16511.99999,16511.99999,16511.99999,16511.99999,0],[1617640848000,16511.99999,16511.99999,16511.99999,16511.99999,0],[1617642649000,16511.99999,16511.99999,16511.99999,16511.99999,0],[1617644450000,16511.99999,16511.99999,16511.99999,16511.99999,0],[1617646251000,16511.99999,16511.99999,16511.99999,16511.99999,0],[1617648052000,16511.99999,16651,16620,16651,0.068786],[1617649853000,16651,16651,16651,16651,0],[1617651654000,16651,16651,16651,16651,0],[1617653455000,16651,16651,16651,16651,0],[1617655256000,16651,16651,16651,16651,0],[1617657057000,16651,16651,16651,16651,0],[1617658858000,16651,16651,16651,16651,0],[1617660659000,16651,16651,16651,16651,0],[1617662460000,16651,16651,16651,16651,0],[1617664261000,16651,16651,16651,16651,0],[1617666062000,16651,16651,16651,16651,0],[1617667863000,16651,17247.999997,16998,17247.999997,0.525059],[1617669664000,17247.999997,17247.999997,17247.999997,17247.999997,0],[1617671465000,17247.999997,17247.999997,17247.999997,17247.999997,0],[1617673266000,17247.999997,17247.999997,17247.999997,17247.999997,0],[1617675067000,17247.999997,17247.999997,17247.999997,17247.999997,0],[1617676868000,17247.999997,17247.999997,17247.999997,17247.999997,0],[1617678669000,17247.999997,17561.999986,17250,17561.999986,0.091992],[1617680470000,17561.999986,17561.999986,17561.999986,17561.999986,0],[1617682271000,17561.999986,17561.999986,17561.999986,17561.999986,0],[1617684072000,17561.999986,17561.999986,17561.999986,17561.999986,0],[1617685873000,17561.999986,17561.999986,17561.999986,17561.999986,0],[1617687674000,17561.999986,17561.999986,17561.999986,17561.999986,0],[1617689475000,17561.999986,17561.999986,17561.999986,17561.999986,0],[1617691276000,17561.999986,17561.999986,17561.999986,17561.999986,0],[1617693077000,17561.999986,17561.999986,17561.999986,17561.999986,0],[1617694878000,17561.999986,16802.5,16802.5,16802.5,0.006254],[1617696679000,16802.5,16802.5,16802.5,16802.5,0],[1617698480000,16802.5,16802.5,16802.5,16802.5,0],[1617700281000,16802.5,16802.5,16802.5,16802.5,0],[1617702082000,16802.5,16665.999848,16617.901021,16617.901021,0.036613],[1617703883000,16617.901021,16617.901021,16617.901021,16617.901021,0],[1617705684000,16617.901021,16384.012005,16384.012005,16384.012005,0.007382],[1617707485000,16384.012005,17500,17300,17300,0.8],[1617709286000,17300,17300,17300,17300,0],[1617711087000,17300,17300,17300,17300,0],[1617712888000,17300,17300,17300,17300,0],[1617714689000,17300,18000.000009,17562.000022,18000.000009,0.087676],[1617716490000,18000.000009,18000.000009,18000.000009,18000.000009,0],[1617718291000,18000.000009,18000.000002,17999.999996,18000.000002,0.112611],[1617720092000,18000.000002,18000.000002,18000.000002,18000.000002,0],[1617721893000,18000.000002,18000.000002,18000.000002,18000.000002,0],[1617723694000,18000.000002,18050.999999,18050,18050.999999,0.030609],[1617725495000,18050.999999,18050.999999,18050.999999,18050.999999,0],[1617727296000,18050.999999,17500,17500,17500,0.29],[1617729097000,17500,17500,17500,17500,0],[1617730898000,17500,16375.999939,15500.999991,15500.999991,0.3],[1617732699000,15500.999991,15500.999991,15500.999991,15500.999991,0],[1617734500000,15500.999991,15500.999991,15500.999991,15500.999991,0],[1617736301000,15500.999991,15500.999991,15500.999991,15500.999991,0],[1617738102000,15500.999991,18500.000012,17990,18500,0.204415],[1617739903000,18500,18500,18500,18500,0],[1617741704000,18500,18500,18500,18500,0.048649],[1617743505000,18500,18500,18500,18500,0],[1617745306000,18500,18500,18500,18500,0],[1617747107000,18500,18500,18500,18500,0],[1617748908000,18500,18500,18500,18500,0],[1617750709000,18500,18500,18500,18500,0],[1617752510000,18500,18500,18500,18500,0],[1617754311000,18500,18500,18500,18500,0],[1617756112000,18500,18500,18500,18500,0],[1617757913000,18500,18500,18500,18500,0],[1617759714000,18500,18500,18500,18500,0],[1617761515000,18500,18500,18500,18500,0],[1617763316000,18500,18500,18500,18500,0],[1617765117000,18500,18500,18500,18500,0],[1617766918000,18500,18500,18500,18500,0],[1617768719000,18500,18500,18500,18500,0],[1617770520000,18500,18500,18500,18500,0],[1617772321000,18500,18500,18500,18500,0],[1617774122000,18500,18500,18500,18500,0],[1617775923000,18500,18230.000021,18229,18230,0.045443],[1617777724000,18230,18251,18229.999998,18251,0.23198],[1617779525000,18251,18605,18498.999991,18500,1.46188],[1617781326000,18500,18500,18500,18500,0.464299],[1617783127000,18500,18505.55,18505.55,18505.55,0.104409],[1617784928000,18505.55,18505,18505,18505,0.1378],[1617786729000,18505,18505,18505,18505,0],[1617788530000,18505,18505,18505,18505,0],[1617790331000,18505,18505,18505,18505,0],[1617792132000,18505,18999.999991,18750.998,18999.999991,0.866742],[1617793933000,18999.999991,19439,18000,18000,0.254941],[1617795734000,18000,18000,18000,18000,0],[1617797535000,18000,18000,18000,18000,0],[1617799336000,18000,18000,18000,18000,0],[1617801137000,18000,18000,18000,18000,0],[1617802938000,18000,17112,17021,17021,0.264],[1617804739000,17021,16701,16700,16700,0.1257],[1617806540000,16700,16700,16700,16700,0],[1617808341000,16700,16700,16700,16700,0],[1617810142000,16700,16700,16700,16700,0],[1617811943000,16700,16700,16700,16700,0],[1617813744000,16700,16285.071006,16221.000031,16221.000031,0.133489],[1617815545000,16221.000031,17800,15305.999995,15305.999995,1.5618],[1617817346000,15305.999995,15305.999995,15305.999995,15305.999995,0],[1617819147000,15305.999995,17300,17200,17200,0.204307],[1617820948000,17200,16270.999955,16270.999955,16270.999955,0.017352],[1617822749000,16270.999955,16270.999955,16270.999955,16270.999955,0],[1617824550000,16270.999955,16270.999955,16270.999955,16270.999955,0],[1617826351000,16270.999955,16270.999955,16270.999955,16270.999955,0],[1617828152000,16270.999955,16270.999955,16270.999955,16270.999955,0],[1617829953000,16270.999955,16270.999955,16270.999955,16270.999955,0],[1617831754000,16270.999955,16270.999955,16270.999955,16270.999955,0],[1617833555000,16270.999955,16270.999955,16270.999955,16270.999955,0],[1617835356000,16270.999955,16270.999955,16270.999955,16270.999955,0],[1617837157000,16270.999955,16270.999955,16270.999955,16270.999955,0],[1617838958000,16270.999955,16270.999955,16270.999955,16270.999955,0],[1617840759000,16270.999955,16270.999955,16270.999955,16270.999955,0],[1617842560000,16270.999955,16270.999955,16270.999955,16270.999955,0],[1617844361000,16270.999955,16270.999955,16270.999955,16270.999955,0],[1617846162000,16270.999955,16270.999955,16270.999955,16270.999955,0],[1617847963000,16270.999955,16270.999955,16270.999955,16270.999955,0],[1617849764000,16270.999955,16270.999955,16270.999955,16270.999955,0],[1617851565000,16270.999955,16640,16400.006009,16400.006009,0.57095],[1617853366000,16400.006009,16400.006009,16400.006009,16400.006009,0],[1617855167000,16400.006009,16400.006009,16400.006009,16400.006009,0],[1617856968000,16400.006009,16400.006009,16400.006009,16400.006009,0],[1617858769000,16400.006009,16400.006009,16400.006009,16400.006009,0],[1617860570000,16400.006009,16400.006009,16400.006009,16400.006009,0],[1617862371000,16400.006009,16400.006009,16400.006009,16400.006009,0],[1617864172000,16400.006009,16400.006009,16400.006009,16400.006009,0],[1617865973000,16400.006009,16400.006009,16400.006009,16400.006009,0],[1617867774000,16400.006009,16400.006009,16400.006009,16400.006009,0],[1617869575000,16400.006009,16400.006009,16400.006009,16400.006009,0],[1617871376000,16400.006009,16400.006009,16400.006009,16400.006009,0],[1617873177000,16400.006009,16400.006009,16400.006009,16400.006009,0],[1617874978000,16400.006009,16400.006009,16400.006009,16400.006009,0],[1617876779000,16400.006009,16943.954743,16943.954743,16943.954743,0.030666],[1617878580000,16943.954743,16842.592093,16699.999997,16699.999997,0.909934],[1617880381000,16699.999997,16699.999997,16699.999997,16699.999997,0],[1617882182000,16699.999997,16699.999997,16699.999997,16699.999997,0],[1617883983000,16699.999997,16699.999997,16699.999997,16699.999997,0],[1617885784000,16699.999997,17285.736639,17285.736639,17285.736639,0.120141],[1617887585000,17285.736639,17285.736639,17285.736639,17285.736639,0],[1617889386000,17285.736639,17285.736639,17285.736639,17285.736639,0],[1617891187000,17285.736639,17285.736639,17285.736639,17285.736639,0],[1617892988000,17285.736639,17285.736639,17285.736639,17285.736639,0],[1617894789000,17285.736639,17285.736639,17285.736639,17285.736639,0],[1617896590000,17285.736639,17300,17300,17300,0.210948],[1617898391000,17300,17300,17300,17300,0],[1617900192000,17300,17300,17300,17300,0],[1617901993000,17300,17300,17300,17300,0],[1617903794000,17300,17300,17300,17300,0],[1617905595000,17300,17300,17300,17300,0],[1617907396000,17300,17300,17300,17300,0],[1617909197000,17300,17300,17300,17300,0],[1617910998000,17300,17300,17300,17300,0],[1617912799000,17300,17300,17300,17300,0],[1617914600000,17300,17300,17300,17300,0],[1617916401000,17300,17300,17300,17300,0],[1617918202000,17300,17599.999991,17451,17599.999991,0.607764],[1617920003000,17599.999991,17599.999991,17599.999991,17599.999991,0],[1617921804000,17599.999991,17599.999991,17599.999991,17599.999991,0],[1617923605000,17599.999991,17599.999991,17599.999991,17599.999991,0],[1617925406000,17599.999991,17599.999991,17599.999991,17599.999991,0],[1617927207000,17599.999991,17599.999991,17599.999991,17599.999991,0],[1617929008000,17599.999991,17599.999991,17599.999991,17599.999991,0],[1617930809000,17599.999991,17599.999991,17599.999991,17599.999991,0],[1617932610000,17599.999991,17599.999991,17599.999991,17599.999991,0],[1617934411000,17599.999991,17599.999991,17599.999991,17599.999991,0],[1617936212000,17599.999991,17599.999991,17599.999991,17599.999991,0],[1617938013000,17599.999991,17599.999991,17599.999991,17599.999991,0],[1617939814000,17599.999991,17599.999991,17599.999991,17599.999991,0],[1617941615000,17599.999991,17599.999991,17599.999991,17599.999991,0],[1617943416000,17599.999991,17599.999991,17599.999991,17599.999991,0],[1617945217000,17599.999991,17599.999991,17599.999991,17599.999991,0],[1617947018000,17599.999991,17599.999991,17599.999991,17599.999991,0],[1617948819000,17599.999991,17599.999991,17599.999991,17599.999991,0],[1617950620000,17599.999991,17599.999991,17599.999991,17599.999991,0],[1617952421000,17599.999991,17599.999991,17599.999991,17599.999991,0],[1617954222000,17599.999991,17599.999991,17599.999991,17599.999991,0],[1617956023000,17599.999991,17599.999991,17599.999991,17599.999991,0],[1617957824000,17599.999991,17599.999991,17599.999991,17599.999991,0],[1617959625000,17599.999991,17599.999991,17599.999991,17599.999991,0],[1617961426000,17599.999991,17599.999991,17599.999991,17599.999991,0],[1617963227000,17599.999991,16850.825202,16750.027004,16750.027004,0.3],[1617965028000,16750.027004,16750.027004,16750.027004,16750.027004,0],[1617966829000,16750.027004,16750.027004,16750.027004,16750.027004,0],[1617968630000,16750.027004,16750.027004,16750.027004,16750.027004,0],[1617970431000,16750.027004,16750.027004,16750.027004,16750.027004,0],[1617972232000,16750.027004,16750.027004,16750.027004,16750.027004,0],[1617974033000,16750.027004,16750.027004,16750.027004,16750.027004,0],[1617975834000,16750.027004,16750.027004,16750.027004,16750.027004,0],[1617977635000,16750.027004,16750.027004,16750.027004,16750.027004,0],[1617979436000,16750.027004,16987.0903,16987.0903,16987.0903,0.002998],[1617981237000,16987.0903,16987.0903,16987.0903,16987.0903,0],[1617983038000,16987.0903,16987.0903,16987.0903,16987.0903,0],[1617984839000,16987.0903,16987.0903,16987.0903,16987.0903,0],[1617986640000,16987.0903,16987.0903,16987.0903,16987.0903,0],[1617988441000,16987.0903,16987.0903,16987.0903,16987.0903,0],[1617990242000,16987.0903,16758.375,16750,16750,0.163366],[1617992043000,16750,16750,16750,16750,0],[1617993844000,16750,16750,16750,16750,0],[1617995645000,16750,16750,16750,16750,0],[1617997446000,16750,16750,16750,16750,0],[1617999247000,16750,16750,16750,16750,0],[1618001048000,16750,16750,16750,16750,0],[1618002849000,16750,16750,16750,16750,0],[1618004650000,16750,16750,16750,16750,0],[1618006451000,16750,17600,17600,17600,0.45],[1618008252000,17600,17600,17600,17600,0],[1618010053000,17600,17600,17600,17600,0],[1618011854000,17600,17600,17600,17600,0],[1618013655000,17600,17600,17600,17600,0],[1618015456000,17600,17600,17600,17600,0],[1618017257000,17600,17600,17600,17600,0],[1618019058000,17600,17600,17600,17600,0],[1618020859000,17600,17600,17600,17600,0],[1618022660000,17600,17600,17600,17600,0],[1618024461000,17600,17600,17600,17600,0],[1618026262000,17600,17600,17600,17600,0],[1618028063000,17600,17600,17600,17600,0],[1618029864000,17600,17607.981991,17607.981991,17607.981991,0.009661],[1618031665000,17607.981991,17607.981991,17607.981991,17607.981991,0],[1618033466000,17607.981991,17607.981991,17607.981991,17607.981991,0],[1618035267000,17607.981991,17607.981991,17607.981991,17607.981991,0],[1618037068000,17607.981991,17607.981991,17607.981991,17607.981991,0],[1618038869000,17607.981991,17608,17608,17608,0.01336],[1618040670000,17608,17608,17608,17608,0],[1618042471000,17608,17995.999998,17700,17995.999998,0.285521],[1618044272000,17995.999998,17995.999998,17995.999998,17995.999998,0],[1618046073000,17995.999998,17606.184693,17606.184693,17606.184693,0.031996],[1618047874000,17606.184693,17606.184693,17606.184693,17606.184693,0],[1618049675000,17606.184693,17606.184693,17606.184693,17606.184693,0],[1618051476000,17606.184693,17606.184693,17606.184693,17606.184693,0],[1618053277000,17606.184693,17606.184693,17606.184693,17606.184693,0],[1618055078000,17606.184693,17606.184693,17606.184693,17606.184693,0],[1618056879000,17606.184693,17606.184693,17606.184693,17606.184693,0],[1618058680000,17606.184693,17606.184693,17606.184693,17606.184693,0],[1618060481000,17606.184693,17606.184693,17606.184693,17606.184693,0],[1618062282000,17606.184693,17606.184693,17606.184693,17606.184693,0],[1618064083000,17606.184693,17606.184693,17606.184693,17606.184693,0],[1618065884000,17606.184693,17606.184693,17606.184693,17606.184693,0],[1618067685000,17606.184693,17606.184693,17606.184693,17606.184693,0],[1618069486000,17606.184693,17606.184693,17606.184693,17606.184693,0],[1618071287000,17606.184693,17606.184693,17606.184693,17606.184693,0],[1618073088000,17606.184693,17606.184693,17606.184693,17606.184693,0],[1618074889000,17606.184693,17606.184693,17606.184693,17606.184693,0],[1618076690000,17606.184693,17725.150787,17225.999999,17225.999999,0.5505],[1618078491000,17225.999999,17225.999999,17225.999999,17225.999999,0],[1618080292000,17225.999999,17225.999999,17225.999999,17225.999999,0],[1618082093000,17225.999999,17225.999999,17225.999999,17225.999999,0],[1618083894000,17225.999999,17225.999999,17225.999999,17225.999999,0],[1618085695000,17225.999999,18686.907464,18003.828649,18003.828649,0.232343],[1618087496000,18003.828649,18003.828649,18003.828649,18003.828649,0],[1618089297000,18003.828649,18003.828649,18003.828649,18003.828649,0],[1618091098000,18003.828649,18450,17300.006009,18450,0.186548],[1618092899000,18450,18450,18450,18450,0],[1618094700000,18450,18450,18450,18450,0],[1618096501000,18450,18450,18450,18450,0],[1618098302000,18450,18450,18450,18450,0],[1618100103000,18450,18450,18450,18450,0],[1618101904000,18450,18450,18450,18450,0],[1618103705000,18450,18450,18450,18450,0],[1618105506000,18450,18450,18450,18450,0],[1618107307000,18450,18450,18450,18450,0],[1618109108000,18450,18450,18450,18450,0],[1618110909000,18450,18450,18450,18450,0],[1618112710000,18450,18450,18450,18450,0],[1618114511000,18450,18450,18450,18450,0],[1618116312000,18450,18790,18450,18790,0.054633],[1618118113000,18790,19200,17862.794263,17862.794263,0.195282],[1618119914000,17862.794263,17862.794263,17862.794263,17862.794263,0],[1618121715000,17862.794263,19289.000003,19289.000003,19289.000003,0.201852],[1618123516000,19289.000003,19398.999984,19288.999994,19398.999984,0.413872],[1618125317000,19398.999984,19398.999984,19398.999984,19398.999984,0],[1618127118000,19398.999984,19398.999984,19398.999984,19398.999984,0],[1618128919000,19398.999984,19398.999984,19398.999984,19398.999984,0],[1618130720000,19398.999984,19398.999984,19398.999984,19398.999984,0],[1618132521000,19398.999984,19398.999984,19398.999984,19398.999984,0],[1618134322000,19398.999984,19306.21895,19306.21895,19306.21895,0.129719],[1618136123000,19306.21895,19306.21895,19306.21895,19306.21895,0],[1618137924000,19306.21895,19306.21895,19306.21895,19306.21895,0],[1618139725000,19306.21895,19306.21895,19306.21895,19306.21895,0],[1618141526000,19306.21895,19306.21895,19306.21895,19306.21895,0],[1618143327000,19306.21895,19306.21895,19306.21895,19306.21895,0],[1618145128000,19306.21895,19304,19304,19304,0.2041],[1618146929000,19304,19304,19304,19304,0],[1618148730000,19304,19304,19304,19304,0],[1618150531000,19304,18836.509698,18836.509698,18836.509698,0.010421],[1618152332000,18836.509698,18836.509698,18836.509698,18836.509698,0],[1618154133000,18836.509698,18836.509698,18836.509698,18836.509698,0],[1618155934000,18836.509698,18836.509698,18836.509698,18836.509698,0],[1618157735000,18836.509698,18836.509698,18836.509698,18836.509698,0.07857],[1618159536000,18836.509698,18836.509698,18836.509698,18836.509698,0],[1618161337000,18836.509698,18836.509698,18836.509698,18836.509698,0],[1618163138000,18836.509698,18836.509698,18836.509698,18836.509698,0],[1618164939000,18836.509698,18836.509698,18836.509698,18836.509698,0],[1618166740000,18836.509698,19461.3397,19216.14334,19461.3397,0.523492],[1618168541000,19461.3397,19461.3397,19461.3397,19461.3397,0],[1618170342000,19461.3397,19461.3397,19461.3397,19461.3397,0],[1618172143000,19461.3397,19461.3397,19461.3397,19461.3397,0],[1618173944000,19461.3397,19461.3397,19461.3397,19461.3397,0],[1618175745000,19461.3397,19461.3397,19461.3397,19461.3397,0],[1618177546000,19461.3397,19916.000002,19461.339696,19916.000002,0.514786],[1618179347000,19916.000002,18355,18355,18355,0.002474],[1618181148000,18355,18355,18355,18355,0],[1618182949000,18355,18369.18,18369.18,18369.18,0.073346],[1618184750000,18369.18,18369.18,18369.18,18369.18,0],[1618186551000,18369.18,18369.18,18369.18,18369.18,0],[1618188352000,18369.18,18369.18,18369.18,18369.18,0],[1618190153000,18369.18,18369.18,18369.18,18369.18,0],[1618191954000,18369.18,18364.1775,18364.1775,18364.1775,0.039481],[1618193755000,18364.1775,19990.000035,19684.65,19990.000035,0.255169],[1618195556000,19990.000035,19990.000035,19990.000035,19990.000035,0],[1618197357000,19990.000035,19990.000035,19990.000035,19990.000035,0],[1618199158000,19990.000035,19990.000035,19990.000035,19990.000035,0],[1618200959000,19990.000035,19990.000035,19990.000035,19990.000035,0],[1618202760000,19990.000035,19990.000035,19990.000035,19990.000035,0],[1618204561000,19990.000035,19990.000035,19990.000035,19990.000035,0],[1618206362000,19990.000035,19990.000035,19990.000035,19990.000035,0],[1618208163000,19990.000035,19990.000035,19990.000035,19990.000035,0],[1618209964000,19990.000035,19990.000035,19990.000035,19990.000035,0],[1618211765000,19990.000035,19990.000035,19990.000035,19990.000035,0],[1618213566000,19990.000035,19990.000035,19990.000035,19990.000035,0],[1618215367000,19990.000035,19990.000035,19990.000035,19990.000035,0],[1618217168000,19990.000035,19990.000035,19990.000035,19990.000035,0],[1618218969000,19990.000035,19990.000035,19990.000035,19990.000035,0],[1618220770000,19990.000035,19990.000035,19990.000035,19990.000035,0],[1618222571000,19990.000035,19990.000035,19990.000035,19990.000035,0],[1618224372000,19990.000035,19990.000035,19990.000035,19990.000035,0],[1618226173000,19990.000035,19990.000035,19990.000035,19990.000035,0],[1618227974000,19990.000035,19990.000035,19990.000035,19990.000035,0],[1618229775000,19990.000035,19990.000035,19990.000035,19990.000035,0],[1618231576000,19990.000035,19990.000035,19990.000035,19990.000035,0],[1618233377000,19990.000035,19990.000035,19990.000035,19990.000035,0],[1618235178000,19990.000035,19990.000035,19990.000035,19990.000035,0],[1618236979000,19990.000035,19990.000035,19990.000035,19990.000035,0],[1618238780000,19990.000035,19990.000035,19990.000035,19990.000035,0],[1618240581000,19990.000035,19990.000035,19990.000035,19990.000035,0],[1618242382000,19990.000035,19990.000035,19990.000035,19990.000035,0],[1618244183000,19990.000035,19990.000035,19990.000035,19990.000035,0],[1618245984000,19990.000035,19990.000035,19990.000035,19990.000035,0],[1618247785000,19990.000035,19005.536808,19005.536808,19005.536808,0.2014],[1618249586000,19005.536808,19005.536808,19005.536808,19005.536808,0],[1618251387000,19005.536808,18364.999991,18364.999991,18364.999991,0.066172],[1618253188000,18364.999991,18366,18355.999866,18355.999866,0.670759],[1618254989000,18355.999866,18355.999866,18355.999866,18355.999866,0],[1618256790000,18355.999866,18355.999866,18355.999866,18355.999866,0],[1618258591000,18355.999866,18355.999866,18355.999866,18355.999866,0],[1618260392000,18355.999866,18355.999866,18355.999866,18355.999866,0],[1618262193000,18355.999866,18355.999866,18355.999866,18355.999866,0],[1618263994000,18355.999866,18355.999866,18355.999866,18355.999866,0],[1618265795000,18355.999866,18355.999866,18355.999866,18355.999866,0],[1618267596000,18355.999866,18355.999866,18355.999866,18355.999866,0],[1618269397000,18355.999866,18355.999866,18355.999866,18355.999866,0],[1618271198000,18355.999866,18355.999866,18355.999866,18355.999866,0],[1618272999000,18355.999866,18355.999866,18355.999866,18355.999866,0],[1618274800000,18355.999866,18355.999866,18355.999866,18355.999866,0],[1618276601000,18355.999866,18355.999866,18355.999866,18355.999866,0],[1618278402000,18355.999866,18355.999866,18355.999866,18355.999866,0],[1618280203000,18355.999866,18355.999866,18355.999866,18355.999866,0],[1618282004000,18355.999866,18355.999866,18355.999866,18355.999866,0],[1618283805000,18355.999866,18355.999866,18355.999866,18355.999866,0],[1618285606000,18355.999866,18355.999866,18355.999866,18355.999866,0],[1618287407000,18355.999866,18355.999866,18355.999866,18355.999866,0],[1618289208000,18355.999866,18355.999866,18355.999866,18355.999866,0],[1618291009000,18355.999866,18355.999866,18355.999866,18355.999866,0],[1618292810000,18355.999866,18355.999866,18355.999866,18355.999866,0],[1618294611000,18355.999866,18355.999866,18355.999866,18355.999866,0],[1618296412000,18355.999866,18355.999866,18355.999866,18355.999866,0],[1618298213000,18355.999866,18355.999866,18355.999866,18355.999866,0],[1618300014000,18355.999866,18355.999866,18355.999866,18355.999866,0],[1618301815000,18355.999866,18355.999866,18355.999866,18355.999866,0],[1618303616000,18355.999866,18355.999866,18355.999866,18355.999866,0],[1618305417000,18355.999866,18355.999866,18355.999866,18355.999866,0],[1618307218000,18355.999866,18355.999866,18355.999866,18355.999866,0],[1618309019000,18355.999866,18355.999866,18355.999866,18355.999866,0],[1618310820000,18355.999866,18355.999866,18355.999866,18355.999866,0],[1618312621000,18355.999866,18355.999866,18355.999866,18355.999866,0],[1618314422000,18355.999866,19499,19499,19499,0.232384],[1618316223000,19499,19499,19499,19499,0],[1618318024000,19499,19505.373,19505.373,19505.373,0.002014],[1618319825000,19505.373,19505.373,19505.373,19505.373,0],[1618321626000,19505.373,19505.373,19505.373,19505.373,0],[1618323427000,19505.373,19541.03,19505.129,19541.03,0.158167],[1618325228000,19541.03,19600.000019,19500,19500,2.0052],[1618327029000,19500,19990,19990,19990,0.112978],[1618328830000,19990,20000.000055,20000.000055,20000.000055,0.01],[1618330631000,20000.000055,20000.000055,20000.000055,20000.000055,0],[1618332432000,20000.000055,20000.000055,20000.000055,20000.000055,0],[1618334233000,20000.000055,19555,19555,19555,0.090969],[1618336034000,19555,19555,19555,19555,0],[1618337835000,19555,19555,19555,19555,0.015176],[1618339636000,19555,20200,20161.339699,20200,0.120575],[1618341437000,20200,19556.862129,19556.862129,19556.862129,0.007063],[1618343238000,19556.862129,20550,20199.999999,20550,3.14859],[1618345039000,20550,20550.000003,20550.000003,20550.000003,0.320271],[1618346840000,20550.000003,20550.000003,20550.000003,20550.000003,0],[1618348641000,20550.000003,20550,20550,20550,0.070821],[1618350442000,20550,20550,20550,20550,0],[1618352243000,20550,20550,20550,20550,0],[1618354044000,20550,20550,20207,20207,0.426197],[1618355845000,20207,20701.000008,20555,20701.000008,0.117641],[1618357646000,20701.000008,20701.000008,20701.000008,20701.000008,0],[1618359447000,20701.000008,20701.000008,20701.000008,20701.000008,0],[1618361248000,20701.000008,20207,20207,20207,0.15588],[1618363049000,20207,20207,20206.059993,20206.059993,1.66962],[1618364850000,20206.059993,20206.059993,20206.059993,20206.059993,0],[1618366651000,20206.059993,20206.059993,20206.059993,20206.059993,0],[1618368452000,20206.059993,20206.059993,20206.059993,20206.059993,0],[1618370253000,20206.059993,20953,20700.999899,20953,0.216794],[1618372054000,20953,21000,20953.000009,21000,0.141054],[1618373855000,21000,21108,21101.33,21108,0.209697],[1618375656000,21108,21995,21499.0005,21995,0.477379],[1618377457000,21995,21995,21995,21995,0],[1618379258000,21995,22000,21994.999863,22000,0.260944],[1618381059000,22000,22000,22000,22000,0],[1618382860000,22000,22000,22000,22000,0.009941],[1618384661000,22000,22000,22000,22000,0],[1618386462000,22000,22000,22000,22000,0],[1618388263000,22000,22000,22000,22000,0],[1618390064000,22000,22000,22000,22000,0],[1618391865000,22000,22880,22880,22880,0.220335],[1618393666000,22880,22880,22880,22880,0],[1618395467000,22880,22880,22880,22880,0],[1618397268000,22880,22900,22900,22900,0.436681],[1618399069000,22900,22900,22900,22900,1.00437],[1618400870000,22900,22900,22900,22900,0],[1618402671000,22900,21664.5,21664.5,21664.5,0.04845],[1618404472000,21664.5,21664.5,20099.000001,20099.000001,0.499782],[1618406273000,20099.000001,20099.000001,20099.000001,20099.000001,0],[1618408074000,20099.000001,22764.500068,22059.601999,22764.500068,0.022512],[1618409875000,22764.500068,22764.500068,22764.500068,22764.500068,0],[1618411676000,22764.500068,21422.902,21422.902,21422.902,0.011751],[1618413477000,21422.902,22600.499991,22600.499991,22600.499991,0.039462],[1618415278000,22600.499991,22500.499991,22400.499991,22400.499991,0.326401],[1618417079000,22400.499991,22400.499991,22400.499991,22400.499991,0],[1618418880000,22400.499991,20629.985,20629.985,20629.985,0.014361],[1618420681000,20629.985,22753.824991,20906.945036,20906.945036,0.135215],[1618422482000,20906.945036,20906.945036,20906.945036,20906.945036,0],[1618424283000,20906.945036,20967.805993,20114.2011,20114.2011,0.25],[1618426084000,20114.2011,22899.999997,22699.999997,22899.999997,1.51396],[1618427885000,22899.999997,22900,22900,22900,0.151726],[1618429686000,22900,22900,22900,22900,0],[1618431487000,22900,22900,22900,22900,0],[1618433288000,22900,22900,22900,22900,0],[1618435089000,22900,22900,22900,22900,0],[1618436890000,22900,22900,22900,22900,0],[1618438691000,22900,21988.455763,21988.455763,21988.455763,0.022501],[1618440492000,21988.455763,21988.455763,21830,21830,1.0175],[1618442293000,21830,21830,21830,21830,0],[1618444094000,21830,21830,21830,21830,0],[1618445895000,21830,21830,21830,21830,0],[1618447696000,21830,21830,21830,21830,0],[1618449497000,21830,21830,21830,21830,0],[1618451298000,21830,21830,21830,21830,0],[1618453099000,21830,21850,21850,21850,0.030984],[1618454900000,21850,21850,21850,21850,0],[1618456701000,21850,21850,21850,21850,0],[1618458502000,21850,22463.732027,22463.732027,22463.732027,0.025294],[1618460303000,22463.732027,22463.732027,22463.732027,22463.732027,0],[1618462104000,22463.732027,22463.732027,22463.732027,22463.732027,0],[1618463905000,22463.732027,22463.732027,22463.732027,22463.732027,0],[1618465706000,22463.732027,22463.732027,22463.732027,22463.732027,0],[1618467507000,22463.732027,22463.732027,22463.732027,22463.732027,0],[1618469308000,22463.732027,22463.732027,22463.732027,22463.732027,0],[1618471109000,22463.732027,22463.732027,22463.732027,22463.732027,0],[1618472910000,22463.732027,21680.496,21680.494455,21680.494455,0.099991],[1618474711000,21680.494455,21680.494455,21680.494455,21680.494455,0],[1618476512000,21680.494455,21680.494455,21680.494455,21680.494455,0],[1618478313000,21680.494455,21680.494455,21680.494455,21680.494455,0],[1618480114000,21680.494455,21680.494455,21680.494455,21680.494455,0],[1618481915000,21680.494455,21680.494455,21680.494455,21680.494455,0],[1618483716000,21680.494455,22108.8,22108.8,22108.8,0.009995],[1618485517000,22108.8,22108.8,22108.8,22108.8,0],[1618487318000,22108.8,22108.8,22108.8,22108.8,0],[1618489119000,22108.8,22108.8,22108.8,22108.8,0],[1618490920000,22108.8,22108.8,22108.8,22108.8,0],[1618492721000,22108.8,22108.8,22108.8,22108.8,0],[1618494522000,22108.8,22108.8,22108.8,22108.8,0],[1618496323000,22108.8,22108.8,22108.8,22108.8,0],[1618498124000,22108.8,22108.8,22108.8,22108.8,0],[1618499925000,22108.8,22108.8,22108.8,22108.8,0],[1618501726000,22108.8,22108.8,22108.8,22108.8,0],[1618503527000,22108.8,23195,23102.320538,23195,0.632729],[1618505328000,23195,23195,23183.408296,23195,0.388161],[1618507129000,23195,23195,23183.408296,23195,0.455049],[1618508930000,23195,24000.000127,23194.999999,24000,0.256019],[1618510731000,24000,24000,24000,24000,0],[1618512532000,24000,24000,24000,24000,0],[1618514333000,24000,24000,24000,24000,0],[1618516134000,24000,22711.35,22711.35,22711.35,0.015387],[1618517935000,22711.35,22711.35,22711.35,22711.35,0],[1618519736000,22711.35,22711.35,22711.35,22711.35,0],[1618521537000,22711.35,22711.35,22711.35,22711.35,0],[1618523338000,22711.35,22711.35,22711.35,22711.35,0],[1618525139000,22711.35,22711.35,22711.35,22711.35,0],[1618526940000,22711.35,24500,24499.999868,24500,0.83],[1618528741000,24500,24500,24500,24500,0],[1618530542000,24500,24500,24500,24500,0],[1618532343000,24500,24500,24500,24500,0],[1618534144000,24500,24500,24500,24500,0],[1618535945000,24500,24500,24500,24500,0],[1618537746000,24500,24500,24500,24500,0],[1618539547000,24500,24500,24500,24500,0],[1618541348000,24500,24500,24500,24500,0],[1618543149000,24500,23460.842976,23460.842976,23460.842976,0.048103],[1618544950000,23460.842976,25000,24600,25000,0.085982],[1618546751000,25000,25000,25000,25000,0],[1618548552000,25000,25000,25000,25000,0],[1618550353000,25000,25000,25000,25000,0],[1618552154000,25000,26000,25500,26000,1.33889],[1618553955000,26000,28000,25999.999965,28000,2.39789],[1618555756000,28000,28000,28000,28000,0],[1618557557000,28000,25599,25599,25599,0.1801],[1618559358000,25599,25599,25599,25599,0],[1618561159000,25599,27999,27999,27999,0.255059],[1618562960000,27999,25007.499998,25007.499998,25007.499998,0.143913],[1618564761000,25007.499998,25007.499998,25007.499998,25007.499998,0],[1618566562000,25007.499998,25007.499998,25007.499998,25007.499998,0],[1618568363000,25007.499998,25007.499998,25007.499998,25007.499998,0],[1618570164000,25007.499998,25007.499998,25007.499998,25007.499998,0],[1618571965000,25007.499998,25007.499998,25007.499998,25007.499998,0],[1618573766000,25007.499998,25007.499998,25007.499998,25007.499998,0],[1618575567000,25007.499998,25007.499998,25007.499998,25007.499998,0],[1618577368000,25007.499998,27700,23874.49,23874.49,0.032646],[1618579169000,23874.49,27700,27700,27700,0.0011],[1618580970000,27700,27700,27700,27700,0],[1618582771000,27700,27700,27700,27700,0],[1618584572000,27700,27700,27700,27700,0],[1618586373000,27700,25000,25000,25000,0.15],[1618588174000,25000,25000,25000,25000,0],[1618589975000,25000,25000,25000,25000,0],[1618591776000,25000,24012.000008,22900.99904,22901,0.20323],[1618593577000,22901,22900.999948,22900.999948,22900.999948,0.001829],[1618595378000,22900.999948,22900.999948,22900.999948,22900.999948,0],[1618597179000,22900.999948,25900,25900,25900,0.03989],[1618598980000,25900,29950,25900,29950,1.98058],[1618600781000,29950,32000.000024,28964.474971,30200,6.94632],[1618602582000,30200,32800.000005,29514.5,31000,1.84472],[1618604383000,31000,31000,30500,30500,0.228066],[1618606184000,30500,30100,29100,29100,0.103],[1618607985000,29100,30580,29489.999999,29490.000003,0.485818],[1618609786000,29490.000003,29490.000003,29490.000003,29490.000003,0],[1618611587000,29490.000003,29011.000017,29000,29000,0.595321],[1618613388000,29000,29000,29000,29000,0],[1618615189000,29000,29000,29000,29000,0],[1618616990000,29000,30580,30580,30580,0.12705],[1618618791000,30580,30580,30580,30580,0],[1618620592000,30580,30580,25599.999997,25599.999997,0.488822],[1618622393000,25599.999997,25599.999997,25599.999997,25599.999997,0],[1618624194000,25599.999997,31750.000001,31700,31750,1.02932],[1618625995000,31750,31750,31750,31750,0],[1618627796000,31750,31750,31750,31750,0],[1618629597000,31750,31750,31750,31750,0],[1618631398000,31750,31750,31750,31750,0],[1618633199000,31750,31750,31750,31750,0],[1618635000000,31750,31750,31750,31750,0],[1618636801000,31750,31750.000006,31750,31750,0.228348],[1618638602000,31750,33410.000118,31999.999991,33410.000118,0.507103],[1618640403000,33410.000118,33410.000118,33410.000118,33410.000118,0],[1618642204000,33410.000118,33410.000118,33410.000118,33410.000118,0],[1618644005000,33410.000118,33410,33410,33410,0.457947],[1618645806000,33410,33410,33410,33410,0],[1618647607000,33410,33410,33410,33410,0],[1618649408000,33410,28200.000007,28200.000007,28200.000007,0.013626],[1618651209000,28200.000007,33300.000026,30000.000108,30000.000108,0.599593],[1618653010000,30000.000108,30000.000108,30000.000108,30000.000108,0],[1618654811000,30000.000108,30000.000108,30000.000108,30000.000108,0],[1618656612000,30000.000108,30000.000108,30000.000108,30000.000108,0],[1618658413000,30000.000108,30000.000108,30000.000108,30000.000108,0],[1618660214000,30000.000108,30000.000108,30000.000108,30000.000108,0],[1618662015000,30000.000108,30000.000108,30000.000108,30000.000108,0],[1618663816000,30000.000108,30307,30307,30307,0.005],[1618665617000,30307,30307,30307,30307,0],[1618667418000,30307,30307,30307,30307,0],[1618669219000,30307,30307,30307,30307,0],[1618671020000,30307,30307,30307,30307,0],[1618672821000,30307,32770.508541,32770.508541,32770.508541,0.001511],[1618674622000,32770.508541,30000,28918.649543,28918.649543,0.025868],[1618676423000,28918.649543,28918.649543,28918.649543,28918.649543,0],[1618678224000,28918.649543,28918.649543,28918.649543,28918.649543,0],[1618680025000,28918.649543,28918.649543,28918.649543,28918.649543,0],[1618681826000,28918.649543,28918.649543,28918.649543,28918.649543,0],[1618683627000,28918.649543,28992.26799,26351.019768,26351.019768,0.548624],[1618685428000,26351.019768,26351.019768,26351.019768,26351.019768,0],[1618687229000,26351.019768,26351.019768,26351.019768,26351.019768,0],[1618689030000,26351.019768,26351.019768,26351.019768,26351.019768,0],[1618690831000,26351.019768,27586.833498,27586.833498,27586.833498,0.34],[1618692632000,27586.833498,29014.931624,28500,29014.931624,0.405],[1618694433000,29014.931624,29023.637117,27737.786886,27737.786886,0.2],[1618696234000,27737.786886,27737.786886,27737.786886,27737.786886,0],[1618698035000,27737.786886,27737.786886,27737.786886,27737.786886,0],[1618699836000,27737.786886,27737.786886,27737.786886,27737.786886,0],[1618701637000,27737.786886,27737.786886,27737.786886,27737.786886,0],[1618703438000,27737.786886,27737.786886,27737.786886,27737.786886,0],[1618705239000,27737.786886,27737.786886,27737.786886,27737.786886,0],[1618707040000,27737.786886,27737.786886,27737.786886,27737.786886,0],[1618708841000,27737.786886,27737.786886,27737.786886,27737.786886,0],[1618710642000,27737.786886,27737.786886,27737.786886,27737.786886,0],[1618712443000,27737.786886,27737.786886,27737.786886,27737.786886,0],[1618714244000,27737.786886,27737.786886,27737.786886,27737.786886,0],[1618716045000,27737.786886,27737.786886,27737.786886,27737.786886,0],[1618717846000,27737.786886,27737.786886,27737.786886,27737.786886,0],[1618719647000,27737.786886,27737.786886,27737.786886,27737.786886,0],[1618721448000,27737.786886,27737.786886,27737.786886,27737.786886,0],[1618723249000,27737.786886,27737.786886,27737.786886,27737.786886,0],[1618725050000,27737.786886,25800,25800,25800,0.024846],[1618726851000,25800,25800,25800,25800,0.108],[1618728652000,25800,25800,25800,25800,0],[1618730453000,25800,25800,25800,25800,0],[1618732254000,25800,25800,25800,25800,0],[1618734055000,25800,25800,25800,25800,0],[1618735856000,25800,25800,25800,25800,0],[1618737657000,25800,25800,25800,25800,0],[1618739458000,25800,25800,25800,25800,0.054603],[1618741259000,25800,26485.757121,26485.757121,26485.757121,0.1],[1618743060000,26485.757121,26485.757121,26485.757121,26485.757121,0],[1618744861000,26485.757121,26485.757121,26485.757121,26485.757121,0.05],[1618746662000,26485.757121,26000,25602,25602,0.68762],[1618748463000,25602,25515,25514.5,25514.5,0.062794],[1618750264000,25514.5,25000,25000,25000,0.005254],[1618752065000,25000,25000,25000,25000,0],[1618753866000,25000,25000,25000,25000,0],[1618755667000,25000,25000,25000,25000,0],[1618757468000,25000,25000,25000,25000,0.017396],[1618759269000,25000,25000,25000,25000,0],[1618761070000,25000,28499.999729,28000,28499.999729,0.008859],[1618762871000,28499.999729,28499.999729,28499.999729,28499.999729,0],[1618764672000,28499.999729,28499.999729,28499.999729,28499.999729,0],[1618766473000,28499.999729,28500,28500,28500,0.175],[1618768274000,28500,28500,28500,28500,0],[1618770075000,28500,28500,28500,28500,0],[1618771876000,28500,28500,28500,28500,0],[1618773677000,28500,25255.840398,25255.840398,25255.840398,0.011349],[1618775478000,25255.840398,25255.840398,25255.840398,25255.840398,0],[1618777279000,25255.840398,25600.898051,25600.898047,25600.89805,0.979441],[1618779080000,25600.89805,25600.89805,25600.89805,25600.89805,0],[1618780881000,25600.89805,25600.89805,25600.89805,25600.89805,0],[1618782682000,25600.89805,25600.89805,25600.89805,25600.89805,0],[1618784483000,25600.89805,25600.89805,25600.89805,25600.89805,0],[1618786284000,25600.89805,25600.89805,25600.89805,25600.89805,0],[1618788085000,25600.89805,25600.89805,25600.89805,25600.89805,0],[1618789886000,25600.89805,25600.89805,25600.89805,25600.89805,0],[1618791687000,25600.89805,25600.89805,25600.89805,25600.89805,0],[1618793488000,25600.89805,25600.89805,25600.89805,25600.89805,0],[1618795289000,25600.89805,25600.89805,25600.89805,25600.89805,0],[1618797090000,25600.89805,28258.470765,28258.470765,28258.470765,0.547219],[1618798891000,28258.470765,28500,28500,28500,0.115789],[1618800692000,28500,28500,28500,28500,0],[1618802493000,28500,28500,28500,28500,0],[1618804294000,28500,28500,28500,28500,0],[1618806095000,28500,28500.000001,28499.999996,28500.000001,1.85349],[1618807896000,28500.000001,28500.000001,28500.000001,28500.000001,0],[1618809697000,28500.000001,28500.000001,28500.000001,28500.000001,0],[1618811498000,28500.000001,28500.000001,28500.000001,28500.000001,0],[1618813299000,28500.000001,28500.000001,28500.000001,28500.000001,0],[1618815100000,28500.000001,28500.000001,28500.000001,28500.000001,0],[1618816901000,28500.000001,28500.000001,28500.000001,28500.000001,0],[1618818702000,28500.000001,27955.297998,27908.54999,27955.297998,0.737378],[1618820503000,27955.297998,29749.999788,27950.685005,29749.999788,0.106074],[1618822304000,29749.999788,29750.000033,29750.000033,29750.000033,0.039062],[1618824105000,29750.000033,30000,30000,30000,0.159421],[1618825906000,30000,30000,30000,30000,0],[1618827707000,30000,28000,27464.448789,27464.448789,0.164066],[1618829508000,27464.448789,27464.448789,27464.448789,27464.448789,0],[1618831309000,27464.448789,27000.1,27000.099996,27000.1,0.825901],[1618833110000,27000.1,27000.1,27000.1,27000.1,0],[1618834911000,27000.1,27000.1,27000.1,27000.1,0],[1618836712000,27000.1,27019.09,26550,26550,1.49782],[1618838513000,26550,26550,26550,26550,0],[1618840314000,26550,27999.999,25374.3466,27999.999,0.115476],[1618842115000,27999.999,26499.999,26499.999,26499.999,0.1],[1618843916000,26499.999,26200.04001,26200.038992,26200.038992,0.125722],[1618845717000,26200.038992,26200.038992,26200.038992,26200.038992,0],[1618847518000,26200.038992,26200.038992,26200.038992,26200.038992,0],[1618849319000,26200.038992,26200.038992,26200.038992,26200.038992,0],[1618851120000,26200.038992,26000,26000,26000,0.2],[1618852921000,26000,26000,26000,26000,0.10423],[1618854722000,26000,25007,24127.757121,24237.8792,0.22008],[1618856523000,24237.8792,24237.8792,24237.8792,24237.8792,0],[1618858324000,24237.8792,24600.001,24500,24500,0.191792],[1618860125000,24500,24500,24500,24500,0],[1618861926000,24500,24500,24500,24500,0],[1618863727000,24500,24500,24500,24500,0],[1618865528000,24500,24500,24500,24500,0],[1618867329000,24500,24500,24500,24500,0],[1618869130000,24500,24500,24500,24500,0],[1618870931000,24500,24500,24500,24500,0],[1618872732000,24500,24500,24500,24500,0],[1618874533000,24500,24500,24500,24500,0],[1618876334000,24500,24500,24500,24500,0],[1618878135000,24500,24500,24500,24500,0],[1618879936000,24500,24500,24500,24500,0],[1618881737000,24500,24500,24500,24500,0],[1618883538000,24500,24500,24500,24500,0],[1618885339000,24500,24500,24500,24500,0],[1618887140000,24500,24500,24500,24500,0],[1618888941000,24500,26000,24099.75715,24099.75715,0.065987],[1618890742000,24099.75715,24099.75715,24099.75715,24099.75715,0],[1618892543000,24099.75715,24099.75715,24099.75715,24099.75715,0],[1618894344000,24099.75715,24099.75715,24099.75715,24099.75715,0],[1618896145000,24099.75715,24099.75715,24099.75715,24099.75715,0],[1618897946000,24099.75715,24099.75715,24099.75715,24099.75715,0],[1618899747000,24099.75715,24099.75715,24099.75715,24099.75715,0],[1618901548000,24099.75715,24099.75715,24099.75715,24099.75715,0],[1618903349000,24099.75715,24099.75715,24099.75715,24099.75715,0],[1618905150000,24099.75715,24099.75715,24099.75715,24099.75715,0],[1618906951000,24099.75715,24099.75715,24099.75715,24099.75715,0],[1618908752000,24099.75715,24099.75715,24099.75715,24099.75715,0],[1618910553000,24099.75715,24099.75715,24099.75715,24099.75715,0],[1618912354000,24099.75715,24099.75715,24099.75715,24099.75715,0],[1618914155000,24099.75715,24099.75715,24099.75715,24099.75715,0],[1618915956000,24099.75715,24099.758,24099.758,24099.758,0.35],[1618917757000,24099.758,24099.758,24099.758,24099.758,0],[1618919558000,24099.758,24099.758,24099.758,24099.758,0],[1618921359000,24099.758,24099.758,24099.758,24099.758,0],[1618923160000,24099.758,24099.758,24099.758,24099.758,0],[1618924961000,24099.758,24099.758,24099.758,24099.758,0],[1618926762000,24099.758,24099.758,24099.758,24099.758,0],[1618928563000,24099.758,24099.758,24099.758,24099.758,0],[1618930364000,24099.758,24099.758,24099.758,24099.758,0],[1618932165000,24099.758,24099.758,24099.758,24099.758,0],[1618933966000,24099.758,24099.758,24099.758,24099.758,0],[1618935767000,24099.758,24099.758,24099.758,24099.758,0],[1618937568000,24099.758,24099.758,24099.758,24099.758,0],[1618939369000,24099.758,24099.758,24099.758,24099.758,0],[1618941170000,24099.758,26000,26000,26000,0.555],[1618942971000,26000,26000,26000,26000,0],[1618944772000,26000,26000,26000,26000,0],[1618946573000,26000,26000,26000,26000,0],[1618948374000,26000,26000,26000,26000,0],[1618950175000,26000,26000,26000,26000,0],[1618951976000,26000,28000,28000,28000,0.003571],[1618953777000,28000,28000,28000,28000,0],[1618955578000,28000,28000,28000,28000,0],[1618957379000,28000,28000,28000,28000,0],[1618959180000,28000,28000,28000,28000,0],[1618960981000,28000,28000,28000,28000,0],[1618962782000,28000,28000,28000,28000,0],[1618964583000,28000,28000,28000,28000,0],[1618966384000,28000,28000,28000,28000,0],[1618968185000,28000,28000,28000,28000,0],[1618969986000,28000,28000,28000,28000,0],[1618971787000,28000,28000,28000,28000,0],[1618973588000,28000,28000,28000,28000,0],[1618975389000,28000,28000,28000,28000,0],[1618977190000,28000,28000,28000,28000,0],[1618978991000,28000,28000,28000,28000,0],[1618980792000,28000,28000,28000,28000,0],[1618982593000,28000,28000,28000,28000,0],[1618984394000,28000,28000,28000,28000,0],[1618986195000,28000,28000,28000,28000,0],[1618987996000,28000,28000,28000,28000,0],[1618989797000,28000,28000,28000,28000,0],[1618991598000,28000,28000,28000,28000,0],[1618993399000,28000,28000,28000,28000,0],[1618995200000,28000,28000,28000,28000,0],[1618997001000,28000,28000,28000,28000,0],[1618998802000,28000,28000,28000,28000,0],[1619000603000,28000,28000,28000,28000,0],[1619002404000,28000,28000,28000,28000,0],[1619004205000,28000,28000,28000,28000,0],[1619006006000,28000,28000,28000,28000,0],[1619007807000,28000,28000,28000,28000,0],[1619009608000,28000,28000,28000,28000,0],[1619011409000,28000,28000,28000,28000,0],[1619013210000,28000,28000,28000,28000,0],[1619015011000,28000,26001,26001,26001,0.1],[1619016812000,26001,26001,26001,26001,0],[1619018613000,26001,26500,26500,26500,0.1],[1619020414000,26500,27000,27000,27000,0.18],[1619022215000,27000,27000,27000,27000,0],[1619024016000,27000,27000,27000,27000,0],[1619025817000,27000,27000,27000,27000,0],[1619027618000,27000,27000,27000,27000,0],[1619029419000,27000,27000,27000,27000,0],[1619031220000,27000,27000,27000,27000,0],[1619033021000,27000,27000,27000,27000,0],[1619034822000,27000,27000,27000,27000,0],[1619036623000,27000,27000,27000,27000,0],[1619038424000,27000,27000,27000,27000,0],[1619040225000,27000,27000,27000,27000,0],[1619042026000,27000,27000,27000,27000,0],[1619043827000,27000,27000,27000,27000,0],[1619045628000,27000,27000,27000,27000,0],[1619047429000,27000,27000,27000,27000,0],[1619049230000,27000,27000,27000,27000,0],[1619051031000,27000,27000,27000,27000,0],[1619052832000,27000,27000,27000,27000,0],[1619054633000,27000,27000,27000,27000,0],[1619056434000,27000,27000,27000,27000,0.005],[1619058235000,27000,27000,27000,27000,0],[1619060036000,27000,27000,27000,27000,0],[1619061837000,27000,27000,27000,27000,0],[1619063638000,27000,27000,27000,27000,0],[1619065439000,27000,27000,27000,27000,0],[1619067240000,27000,27000,27000,27000,0],[1619069041000,27000,27000,27000,27000,0],[1619070842000,27000,27000,27000,27000,0],[1619072643000,27000,27000,27000,27000,0],[1619074444000,27000,27000,27000,27000,0],[1619076245000,27000,27000,27000,27000,0],[1619078046000,27000,27000,27000,27000,0],[1619079847000,27000,27000,27000,27000,0],[1619081648000,27000,27988.999993,27585.304,27988.999993,0.123892],[1619083449000,27988.999993,27988.999993,27988.999993,27988.999993,0],[1619085250000,27988.999993,27988.999993,27988.999993,27988.999993,0],[1619087051000,27988.999993,27988.999993,27988.999993,27988.999993,0],[1619088852000,27988.999993,27988.999993,27988.999993,27988.999993,0],[1619090653000,27988.999993,27988.999993,27988.999993,27988.999993,0],[1619092454000,27988.999993,27988.999993,27988.999993,27988.999993,0],[1619094255000,27988.999993,27988.999993,27988.999993,27988.999993,0],[1619096056000,27988.999993,27988.999993,27988.999993,27988.999993,0],[1619097857000,27988.999993,27988.999993,27988.999993,27988.999993,0],[1619099658000,27988.999993,27988.999993,27988.999993,27988.999993,0],[1619101459000,27988.999993,27988.999993,27988.999993,27988.999993,0],[1619103260000,27988.999993,27988.999993,27988.999993,27988.999993,0],[1619105061000,27988.999993,27988.999993,27988.999993,27988.999993,0],[1619106862000,27988.999993,27988.999993,27988.999993,27988.999993,0],[1619108663000,27988.999993,27988.999993,27988.999993,27988.999993,0],[1619110464000,27988.999993,27988.999993,27988.999993,27988.999993,0],[1619112265000,27988.999993,27988.999993,27988.999993,27988.999993,0],[1619114066000,27988.999993,27988.999993,27988.999993,27988.999993,0],[1619115867000,27988.999993,27988.999993,27988.999993,27988.999993,0],[1619117668000,27988.999993,27988.999993,27988.999993,27988.999993,0],[1619119469000,27988.999993,27988.999993,27988.999993,27988.999993,0],[1619121270000,27988.999993,27988.999993,27988.999993,27988.999993,0],[1619123071000,27988.999993,27988.999993,27988.999993,27988.999993,0],[1619124872000,27988.999993,27988.999993,27988.999993,27988.999993,0],[1619126673000,27988.999993,27988.999993,27988.999993,27988.999993,0],[1619128474000,27988.999993,24451.628,24451.628,24451.628,0.012903],[1619130275000,24451.628,24451.628,24451.628,24451.628,0],[1619132076000,24451.628,24451.628,24451.628,24451.628,0],[1619133877000,24451.628,24451.628,24451.628,24451.628,0],[1619135678000,24451.628,24451.628,24451.628,24451.628,0],[1619137479000,24451.628,24451.628,24451.628,24451.628,0],[1619139280000,24451.628,24451.628,24451.628,24451.628,0],[1619141081000,24451.628,24451.628,24451.628,24451.628,0],[1619142882000,24451.628,24451.628,24451.628,24451.628,0],[1619144683000,24451.628,24451.628,24451.628,24451.628,0],[1619146484000,24451.628,24451.628,24451.628,24451.628,0],[1619148285000,24451.628,24451.628,24451.628,24451.628,0],[1619150086000,24451.628,24099.757122,24099.757122,24099.757122,0.06693],[1619151887000,24099.757122,24000,23045.000114,23045.000114,0.060464],[1619153688000,23045.000114,23045.000009,22860.000003,22860.000003,0.884394],[1619155489000,22860.000003,22860,22860,22860,0.408685],[1619157290000,22860,22860,22860,22860,0],[1619159091000,22860,22860,22860,22860,0],[1619160892000,22860,22860,22860,22860,0],[1619162693000,22860,22860,22860,22860,0.267837],[1619164494000,22860,22860,22860,22860,0],[1619166295000,22860,22860,22860,22860,0],[1619168096000,22860,22860,22860,22860,0],[1619169897000,22860,22860,22860,22860,0],[1619171698000,22860,20518.08113,20518.08113,20518.08113,0.029985],[1619173499000,20518.08113,20518.08113,20518.08113,20518.08113,0],[1619175300000,20518.08113,20518.08113,20518.08113,20518.08113,0],[1619177101000,20518.08113,20518.08113,20518.08113,20518.08113,0],[1619178902000,20518.08113,26497.61887,23458.399,23458.399,0.166655],[1619180703000,23458.399,23458.399,23458.399,23458.399,0],[1619182504000,23458.399,23458.399,23458.399,23458.399,0],[1619184305000,23458.399,23458.399,23458.399,23458.399,0],[1619186106000,23458.399,25885,25885,25885,0.015],[1619187907000,25885,25885,25885,25885,0],[1619189708000,25885,25885,25885,25885,0],[1619191509000,25885,25885,25885,25885,0],[1619193310000,25885,25885,25885,25885,0],[1619195111000,25885,25885,25885,25885,0],[1619196912000,25885,25885,25885,25885,0],[1619198713000,25885,25885,25885,25885,0],[1619200514000,25885,21975.17,21975.17,21975.17,0.003908],[1619202315000,21975.17,21975.17,21975.17,21975.17,0],[1619204116000,21975.17,21975.17,21975.17,21975.17,0],[1619205917000,21975.17,21975.17,21975.17,21975.17,0],[1619207718000,21975.17,21975.17,21975.17,21975.17,0],[1619209519000,21975.17,23953.304,23953.304,23953.304,0.003703],[1619211320000,23953.304,23953.304,23953.304,23953.304,0],[1619213121000,23953.304,23953.304,23953.304,23953.304,0],[1619214922000,23953.304,23953.304,23953.304,23953.304,0],[1619216723000,23953.304,23953.304,23953.304,23953.304,0],[1619218524000,23953.304,23953.304,23953.304,23953.304,0],[1619220325000,23953.304,23953.304,23953.304,23953.304,0],[1619222126000,23953.304,23953.304,23953.304,23953.304,0],[1619223927000,23953.304,23953.304,23953.304,23953.304,0],[1619225728000,23953.304,23953.304,23953.304,23953.304,0],[1619227529000,23953.304,23953.304,23953.304,23953.304,0],[1619229330000,23953.304,23953.304,23953.304,23953.304,0],[1619231131000,23953.304,23953.304,23953.304,23953.304,0],[1619232932000,23953.304,23953.304,23953.304,23953.304,0],[1619234733000,23953.304,23953.304,23953.304,23953.304,0],[1619236534000,23953.304,23953.304,23953.304,23953.304,0],[1619238335000,23953.304,23953.304,23953.304,23953.304,0],[1619240136000,23953.304,23953.304,23953.304,23953.304,0],[1619241937000,23953.304,23953.304,23953.304,23953.304,0],[1619243738000,23953.304,23953.304,23953.304,23953.304,0],[1619245539000,23953.304,22616.982153,22616.982153,22616.982153,0.300305],[1619247340000,22616.982153,22417.459878,22417.459878,22417.459878,0.042],[1619249141000,22417.459878,22417.459878,22417.459878,22417.459878,0],[1619250942000,22417.459878,22417.459878,22417.459878,22417.459878,0],[1619252743000,22417.459878,22417.459878,22417.459878,22417.459878,0],[1619254544000,22417.459878,22417.459878,22417.459878,22417.459878,0],[1619256345000,22417.459878,22417.459878,22417.459878,22417.459878,0],[1619258146000,22417.459878,22417.459878,22417.459878,22417.459878,0],[1619259947000,22417.459878,22417.459878,22417.459878,22417.459878,0],[1619261748000,22417.459878,22417.459878,22417.459878,22417.459878,0],[1619263549000,22417.459878,22417.459878,22417.459878,22417.459878,0],[1619265350000,22417.459878,22417.459878,22417.459878,22417.459878,0],[1619267151000,22417.459878,22417.459878,22417.459878,22417.459878,0],[1619268952000,22417.459878,22417.459878,22417.459878,22417.459878,0],[1619270753000,22417.459878,22417.459878,22417.459878,22417.459878,0],[1619272554000,22417.459878,22177,22001,22001,0.09906],[1619274355000,22001,22001,22001,22001,0],[1619276156000,22001,22001,22001,22001,0],[1619277957000,22001,22001,22001,22001,0],[1619279758000,22001,22001,22001,22001,0],[1619281559000,22001,22001,22001,22001,0],[1619283360000,22001,22001,22001,22001,0],[1619285161000,22001,22001,22001,22001,0],[1619286962000,22001,22001,22001,22001,0],[1619288763000,22001,22001,22001,22001,0],[1619290564000,22001,22001,22001,22001,0],[1619292365000,22001,22001,22001,22001,0],[1619294166000,22001,22001,22001,22001,0],[1619295967000,22001,22001,22001,22001,0],[1619297768000,22001,22001,22001,22001,0],[1619299569000,22001,22001,22001,22001,0],[1619301370000,22001,22001,22001,22001,0],[1619303171000,22001,23969.00009,23551.166,23556.879,0.38095],[1619304972000,23556.879,23547.027,23476.293,23476.293,0.349197],[1619306773000,23476.293,23476.293,23476.293,23476.293,0],[1619308574000,23476.293,23476.293,23476.293,23476.293,0],[1619310375000,23476.293,23476.293,23476.293,23476.293,0],[1619312176000,23476.293,23476.293,23476.293,23476.293,0],[1619313977000,23476.293,23476.293,23476.293,23476.293,0],[1619315778000,23476.293,23476.293,23476.293,23476.293,0],[1619317579000,23476.293,23476.293,23476.293,23476.293,0],[1619319380000,23476.293,23476.293,23476.293,23476.293,0],[1619321181000,23476.293,23476.293,23476.293,23476.293,0],[1619322982000,23476.293,23476.293,23476.293,23476.293,0],[1619324783000,23476.293,23476.293,23476.293,23476.293,0],[1619326584000,23476.293,23476.293,23476.293,23476.293,0],[1619328385000,23476.293,23476.293,23476.293,23476.293,0],[1619330186000,23476.293,23476.293,23476.293,23476.293,0],[1619331987000,23476.293,23476.293,23476.293,23476.293,0],[1619333788000,23476.293,23476.293,23476.293,23476.293,0],[1619335589000,23476.293,23476.293,23476.293,23476.293,0],[1619337390000,23476.293,23476.293,23476.293,23476.293,0],[1619339191000,23476.293,23476.293,23476.293,23476.293,0],[1619340992000,23476.293,23476.293,23476.293,23476.293,0],[1619342793000,23476.293,23476.293,23476.293,23476.293,0],[1619344594000,23476.293,23476.293,23476.293,23476.293,0],[1619346395000,23476.293,23476.293,23476.293,23476.293,0],[1619348196000,23476.293,21976,21976,21976,0.012381],[1619349997000,21976,21976,21976,21976,0],[1619351798000,21976,21976,21976,21976,0],[1619353599000,21976,21976,21976,21976,0],[1619355400000,21976,21976,21976,21976,0],[1619357201000,21976,21976,21976,21976,0],[1619359002000,21976,23171.265,23171.265,23171.265,0.021578],[1619360803000,23171.265,23171.265,23171.265,23171.265,0],[1619362604000,23171.265,23171.265,23171.265,23171.265,0],[1619364405000,23171.265,23171.265,23171.265,23171.265,0],[1619366206000,23171.265,23171.265,23171.265,23171.265,0],[1619368007000,23171.265,23171.265,23171.265,23171.265,0],[1619369808000,23171.265,23171.265,23171.265,23171.265,0],[1619371609000,23171.265,23171.265,23171.265,23171.265,0],[1619373410000,23171.265,23171.265,23171.265,23171.265,0],[1619375211000,23171.265,23171.265,23171.265,23171.265,0],[1619377012000,23171.265,23171.265,23171.265,23171.265,0],[1619378813000,23171.265,23171.265,23171.265,23171.265,0],[1619380614000,23171.265,23171.265,23171.265,23171.265,0],[1619382415000,23171.265,23171.265,23171.265,23171.265,0],[1619384216000,23171.265,23171.265,23171.265,23171.265,0],[1619386017000,23171.265,23171.265,23171.265,23171.265,0],[1619387818000,23171.265,23171.265,23171.265,23171.265,0],[1619389619000,23171.265,23171.265,23171.265,23171.265,0],[1619391420000,23171.265,23171.265,23171.265,23171.265,0],[1619393221000,23171.265,23171.265,23171.265,23171.265,0],[1619395022000,23171.265,23171.265,23171.265,23171.265,0],[1619396823000,23171.265,21976,21975.17,21975.17,0.018711],[1619398624000,21975.17,21975.17,21975.17,21975.17,0],[1619400425000,21975.17,21975.17,21975.17,21975.17,0],[1619402226000,21975.17,21975.17,21975.17,21975.17,0],[1619404027000,21975.17,21975.17,21975.17,21975.17,0],[1619405828000,21975.17,21975.17,21975.17,21975.17,0],[1619407629000,21975.17,21975.17,21975.17,21975.17,0],[1619409430000,21975.17,21975.17,21975.17,21975.17,0],[1619411231000,21975.17,21975.17,21975.17,21975.17,0],[1619413032000,21975.17,21975.17,21975.17,21975.17,0],[1619414833000,21975.17,21975.17,21975.17,21975.17,0],[1619416634000,21975.17,21975.17,21975.17,21975.17,0],[1619418435000,21975.17,21975.17,21975.17,21975.17,0],[1619420236000,21975.17,21975.17,21975.17,21975.17,0],[1619422037000,21975.17,21975.17,21975.17,21975.17,0],[1619423838000,21975.17,21975.17,21975.17,21975.17,0],[1619425639000,21975.17,21975.17,21975.17,21975.17,0],[1619427440000,21975.17,21975.17,21975.17,21975.17,0],[1619429241000,21975.17,21975.17,21975.17,21975.17,0],[1619431042000,21975.17,21975.17,21975.17,21975.17,0],[1619432843000,21975.17,21975.17,21975.17,21975.17,0],[1619434644000,21975.17,21975.17,21975.17,21975.17,0],[1619436445000,21975.17,21975.17,21975.17,21975.17,0],[1619438246000,21975.17,21975.17,21975.17,21975.17,0],[1619440047000,21975.17,21975.17,21975.17,21975.17,0],[1619441848000,21975.17,21975.17,21975.17,21975.17,0],[1619443649000,21975.17,21975.17,21975.17,21975.17,0],[1619445450000,21975.17,21975.17,21975.17,21975.17,0],[1619447251000,21975.17,21717,20574.518894,20574.518894,1.30258],[1619449052000,20574.518894,20574.518894,20574.518894,20574.518894,0],[1619450853000,20574.518894,20574.518894,20574.518894,20574.518894,0],[1619452654000,20574.518894,20574.518894,20574.518894,20574.518894,0],[1619454455000,20574.518894,24398,24398,24398,0.031454],[1619456256000,24398,24398,24398,24398,0],[1619458057000,24398,24398,24398,24398,0],[1619459858000,24398,24398,24398,24398,0],[1619461659000,24398,24398,24398,24398,0],[1619463460000,24398,24398,24398,24398,0],[1619465261000,24398,24398,24398,24398,0],[1619467062000,24398,24398,24398,24398,0],[1619468863000,24398,24398,24398,24398,0],[1619470664000,24398,24398,24398,24398,0],[1619472465000,24398,24398,24398,24398,0.03316],[1619474266000,24398,24398,24398,24398,0],[1619476067000,24398,24398,24398,24398,0],[1619477868000,24398,24398,24398,24398,0],[1619479669000,24398,24398,24398,24398,0],[1619481470000,24398,24398,24398,24398,0],[1619483271000,24398,24398,24398,24398,0],[1619485072000,24398,24398,24398,24398,0],[1619486873000,24398,24398,24398,24398,0],[1619488674000,24398,24398,24398,24398,0],[1619490475000,24398,24398,24398,24398,0],[1619492276000,24398,24398,24398,24398,0],[1619494077000,24398,24398,24398,24398,0],[1619495878000,24398,24398,24398,24398,0],[1619497679000,24398,24398,24398,24398,0],[1619499480000,24398,24398,24398,24398,0],[1619501281000,24398,24398,24398,24398,0],[1619503082000,24398,24398,24398,24398,0],[1619504883000,24398,24398,24398,24398,0],[1619506684000,24398,24398,24398,24398,0],[1619508485000,24398,24398,24398,24398,0],[1619510286000,24398,24398,24398,24398,0],[1619512087000,24398,24398,24398,24398,0],[1619513888000,24398,24398,24398,24398,0],[1619515689000,24398,24398,24398,24398,0.0178],[1619517490000,24398,24398,24398,24398,0],[1619519291000,24398,24398,24398,24398,0],[1619521092000,24398,24398,24398,24398,0],[1619522893000,24398,24398,24398,24398,0],[1619524694000,24398,24398,24398,24398,0],[1619526495000,24398,24398,24398,24398,0],[1619528296000,24398,24398,24398,24398,0],[1619530097000,24398,24398,24398,24398,0],[1619531898000,24398,24398,24398,24398,0],[1619533699000,24398,24436.964269,24436.964269,24436.964269,0.066419],[1619535500000,24436.964269,24436.964269,24436.964269,24436.964269,0],[1619537301000,24436.964269,24436.964269,24436.964269,24436.964269,0],[1619539102000,24436.964269,24436.964269,24436.964269,24436.964269,0],[1619540903000,24436.964269,24436.964269,24436.964269,24436.964269,0],[1619542704000,24436.964269,24444.999,24444.999,24444.999,0.535],[1619544505000,24444.999,24444.999,24444.999,24444.999,0],[1619546306000,24444.999,24444.999,24444.999,24444.999,0],[1619548107000,24444.999,24444.999,24444.999,24444.999,0],[1619549908000,24444.999,24444.999,24444.999,24444.999,0]]}},"tickers":{"statusCode":501,"response":""},"orderBook":{"statusCode":200,"response":{"bids":[{"price":24444.295,"amount":0.000019918689},{"price":23409.0304,"amount":0.341748456186},{"price":23408.0404999999,"amount":1.134064792214},{"price":23401,"amount":0.0468},{"price":23398,"amount":0.02222412},{"price":22800,"amount":0.043644466909},{"price":21399,"amount":0.170396002075},{"price":21000,"amount":0.1},{"price":20562.4579939077,"amount":0.993081907136},{"price":20500,"amount":0.1501},{"price":20350,"amount":0.00122},{"price":20300,"amount":0.133875340459},{"price":20100,"amount":0.1501},{"price":20001,"amount":0.02869381},{"price":20000,"amount":0.015},{"price":19991,"amount":0.011},{"price":19613,"amount":0.204151456206},{"price":19612,"amount":0.281395693374},{"price":19505.85,"amount":0.000099910027},{"price":18881,"amount":0.015},{"price":18550,"amount":0.0269069},{"price":18501,"amount":0.258571619903},{"price":18485.757121,"amount":0.015},{"price":18410,"amount":0.2},{"price":18085,"amount":0.027643506221},{"price":18084,"amount":0.02761404457},{"price":18082,"amount":0.027436124323},{"price":18061.0000001,"amount":0.20888246},{"price":17808,"amount":0.027995283019},{"price":17801,"amount":0.028},{"price":17800,"amount":0.05},{"price":17771,"amount":0.014},{"price":17771,"amount":0.025},{"price":17500,"amount":0.05},{"price":17305,"amount":0.098},{"price":17171,"amount":0.015},{"price":16702,"amount":0.029926415998},{"price":16571,"amount":0.025},{"price":16570,"amount":0.09885938},{"price":16061,"amount":0.0251},{"price":16053,"amount":0.101451438864},{"price":15800,"amount":0.05},{"price":15602,"amount":0.048724518822},{"price":15551,"amount":0.0207},{"price":15502,"amount":0.05},{"price":15500,"amount":0.05},{"price":15485.757121,"amount":0.01},{"price":15350,"amount":0.05},{"price":15052,"amount":0.05},{"price":15051,"amount":0.019},{"price":14840,"amount":0.1},{"price":14789,"amount":0.02},{"price":14307,"amount":0.05},{"price":14305,"amount":0.0698121},{"price":14141,"amount":0.0141},{"price":13884.557999,"amount":0.0155},{"price":13813,"amount":0.02},{"price":13305,"amount":0.1},{"price":12884.557999,"amount":0.017},{"price":12002,"amount":0.27290228},{"price":12000,"amount":0.11},{"price":11700,"amount":0.049786324786},{"price":11150,"amount":0.035603547632},{"price":11135,"amount":0.0181},{"price":11100,"amount":0.009},{"price":11000,"amount":0.11},{"price":10835,"amount":0.02},{"price":10535,"amount":0.018},{"price":10355,"amount":0.019},{"price":10250,"amount":0.049041962439},{"price":10211,"amount":0.01971963},{"price":10101,"amount":0.0211},{"price":10000,"amount":0.11},{"price":9966,"amount":0.0235},{"price":9840,"amount":0.07994017},{"price":9779,"amount":0.02},{"price":9669,"amount":0.02208},{"price":9559,"amount":0.020956},{"price":9393,"amount":0.0225},{"price":9191,"amount":0.022},{"price":8200,"amount":0.19022588},{"price":8169,"amount":0.149021053777},{"price":7255,"amount":0.07707839},{"price":6960,"amount":0.05},{"price":6851,"amount":0.08389439},{"price":6226,"amount":0.0123},{"price":5700,"amount":0.48350877},{"price":5500,"amount":0.05},{"price":5372,"amount":0.042514},{"price":4832.11,"amount":0.0177438},{"price":4612,"amount":0.01031652},{"price":3942,"amount":0.136853},{"price":2430,"amount":0.244279850206},{"price":1100,"amount":0.05},{"price":1000,"amount":0.008},{"price":200,"amount":0.0047},{"price":120,"amount":0.6455211},{"price":100,"amount":0.9},{"price":30,"amount":1.97},{"price":25.01,"amount":5},{"price":25,"amount":5},{"price":2.5,"amount":7},{"price":2.15,"amount":4.93413955},{"price":2.01,"amount":1.246272},{"price":1.7,"amount":7},{"price":1.1,"amount":50},{"price":1.05,"amount":100},{"price":1,"amount":10},{"price":1,"amount":1},{"price":1,"amount":1},{"price":1,"amount":0.11},{"price":1,"amount":100.5},{"price":0.13,"amount":0.1},{"price":0.05,"amount":266.350868},{"price":0.04989,"amount":100},{"price":0.04989,"amount":179},{"price":0.04989,"amount":57},{"price":0.04989,"amount":10},{"price":0.00004,"amount":1},{"price":0.0000026495,"amount":100000.00000000001}],"asks":[{"price":24995,"amount":0.06032586},{"price":25444.2949999999,"amount":0.1347325},{"price":25694.2949999999,"amount":0.1},{"price":26759,"amount":0.01867},{"price":26760,"amount":0.01859},{"price":26765,"amount":0.0149},{"price":26770,"amount":0.0186601997},{"price":26775,"amount":0.018649322},{"price":26778,"amount":0.01864},{"price":26780,"amount":0.01865},{"price":26798,"amount":0.01153951},{"price":26799,"amount":0.2},{"price":26800,"amount":0.2976233},{"price":27688,"amount":0.025898},{"price":27990,"amount":0.00446776},{"price":28500,"amount":0.01145188},{"price":29702.593,"amount":0.0013993},{"price":29990,"amount":0.01225},{"price":30000,"amount":0.00989505},{"price":31000,"amount":0.049975},{"price":32790,"amount":0.01312023},{"price":33333,"amount":0.03998},{"price":33333,"amount":0.0011927},{"price":33600,"amount":0.001},{"price":33800,"amount":0.001},{"price":34000,"amount":0.001},{"price":34000,"amount":0.001},{"price":34200,"amount":0.001},{"price":34400,"amount":0.001},{"price":34600,"amount":0.001},{"price":34800,"amount":0.001},{"price":34988.98943,"amount":0.54721008},{"price":34989.98943,"amount":0.5},{"price":35000,"amount":0.001},{"price":35200,"amount":0.001},{"price":35400,"amount":0.001},{"price":35600,"amount":0.001},{"price":35800,"amount":0.001},{"price":36000,"amount":0.001},{"price":36000,"amount":0.001},{"price":36200,"amount":0.001},{"price":36400,"amount":0.001},{"price":36600,"amount":0.001},{"price":36800,"amount":0.001},{"price":36890,"amount":1},{"price":37000,"amount":0.001},{"price":37200,"amount":0.001},{"price":37400,"amount":0.001},{"price":37600,"amount":0.001},{"price":37800,"amount":0.001},{"price":37989.98943,"amount":0.5},{"price":38000,"amount":0.001},{"price":38000,"amount":0.001},{"price":38200,"amount":0.001},{"price":38331.177966,"amount":0.00150996},{"price":38400,"amount":0.001},{"price":38600,"amount":0.001},{"price":38800,"amount":0.001},{"price":38899.99883,"amount":0.35},{"price":39000,"amount":0.001},{"price":39200,"amount":0.001},{"price":39399.99393,"amount":0.44801212},{"price":39400,"amount":0.001},{"price":39600,"amount":0.001},{"price":39800,"amount":0.001},{"price":39876,"amount":0.03537469},{"price":39899.99893,"amount":0.262524},{"price":40000,"amount":0.001},{"price":40000,"amount":0.001},{"price":40200,"amount":0.001},{"price":40400,"amount":0.001},{"price":40600,"amount":0.001},{"price":40800,"amount":0.001},{"price":40899.99804,"amount":0.35},{"price":41000,"amount":0.001},{"price":41005.5,"amount":0.1},{"price":41200,"amount":0.001},{"price":41400,"amount":0.001},{"price":41600,"amount":0.001},{"price":41800,"amount":0.012014},{"price":41800,"amount":0.001},{"price":42000,"amount":0.001},{"price":42000,"amount":0.001},{"price":42200,"amount":0.001},{"price":42400,"amount":0.001},{"price":42499,"amount":0.01770897},{"price":42600,"amount":0.001},{"price":42800,"amount":0.001},{"price":43000,"amount":0.001},{"price":43200,"amount":0.001},{"price":43400,"amount":0.001},{"price":43600,"amount":0.001},{"price":43800,"amount":0.001},{"price":43810,"amount":0.10885854},{"price":44000,"amount":0.001},{"price":44000,"amount":0.001},{"price":44000,"amount":1},{"price":44200,"amount":0.001},{"price":44400,"amount":0.001},{"price":44415,"amount":0.11051871},{"price":44540,"amount":0.13385394},{"price":44600,"amount":0.001},{"price":44800,"amount":0.001},{"price":45000,"amount":0.00155658},{"price":46000,"amount":0.001},{"price":48000,"amount":0.001},{"price":48850.099999,"amount":1},{"price":50000,"amount":0.00309966},{"price":50000,"amount":0.001},{"price":50005,"amount":0.00547483},{"price":53000,"amount":0.05083433},{"price":54000,"amount":0.001},{"price":55000,"amount":0.00168898},{"price":55519,"amount":1},{"price":56499,"amount":0.05},{"price":57900,"amount":0.33542},{"price":58000,"amount":0.001},{"price":58850.099999,"amount":1},{"price":58962.109539,"amount":0.00100949},{"price":60000,"amount":0.09995},{"price":60783,"amount":0.03634581},{"price":62000,"amount":0.29985},{"price":62000,"amount":0.001},{"price":64400,"amount":0.00329935},{"price":65750,"amount":0.00104047},{"price":66000,"amount":0.001},{"price":66000,"amount":0.001},{"price":66003.01,"amount":0.001999},{"price":66200.01,"amount":0.049975},{"price":69000,"amount":0.001},{"price":69000,"amount":0.115},{"price":70000,"amount":0.001},{"price":70900,"amount":0.059969},{"price":71450,"amount":0.007},{"price":72000,"amount":0.9995},{"price":73500,"amount":0.03090753},{"price":78244,"amount":0.02886755},{"price":78850.099999,"amount":1},{"price":80000,"amount":0.0050075},{"price":80000,"amount":0.00991762},{"price":81000,"amount":0.11994088},{"price":84000.75712,"amount":0.2256562},{"price":84347,"amount":0.015},{"price":85000,"amount":0.02},{"price":85000,"amount":0.05},{"price":87000,"amount":0.02},{"price":87198,"amount":0.002},{"price":88000,"amount":0.02},{"price":89000,"amount":0.02},{"price":90000,"amount":0.02},{"price":90000,"amount":0.00848476},{"price":90000,"amount":0.05431682},{"price":90000,"amount":0.05993301},{"price":95000,"amount":0.01},{"price":98524,"amount":0.12864265},{"price":98850.099999,"amount":1},{"price":100099,"amount":0.0049975},{"price":102000,"amount":0.04},{"price":107000,"amount":0.027975},{"price":109999,"amount":0.012},{"price":115012,"amount":0.00522613},{"price":117111,"amount":0.01096052},{"price":120000,"amount":0.00109945},{"price":120000,"amount":0.2776},{"price":123000,"amount":0.00109945},{"price":128850.099999,"amount":1},{"price":145254,"amount":0.101},{"price":150900,"amount":0.005},{"price":151000,"amount":0.00150124},{"price":167897,"amount":0.1035},{"price":170000,"amount":0.0328237},{"price":183552,"amount":0.073952},{"price":230000,"amount":0.0049975},{"price":511500,"amount":0.031},{"price":699000,"amount":0.126916},{"price":894800,"amount":0.02},{"price":999999,"amount":0.4},{"price":2412000,"amount":0.01},{"price":5900000,"amount":0.03}]}},"trades":{"statusCode":200,"response":[{"id":"6361981","info":{"amnt_base":"1623.0735979941","order_id":176551857,"unixtime":1619524222,"price":"24436.9642686068","amnt_trade":"0.0664187900","user":"newminer7950","type":"buy","pub_date":"27  2021 . 14:50","id":6361981},"timestamp":1619524200000,"datetime":"2021-04-27T11:50:00.000Z","symbol":"BCH/UAH","side":"buy","price":24436.9642686068,"amount":0.06641879},{"id":"6362347","info":{"amnt_base":"3324.5198640000","order_id":176570158,"unixtime":1619531916,"price":"24444.9990000000","amnt_trade":"0.1360000000","user":"newminer7950","type":"sell","pub_date":"27  2021 . 16:58","id":6362347},"timestamp":1619531880000,"datetime":"2021-04-27T13:58:00.000Z","symbol":"BCH/UAH","side":"sell","price":24444.999,"amount":0.136},{"id":"6362341","info":{"amnt_base":"9753.5546010000","order_id":176570152,"unixtime":1619531912,"price":"24444.9990000000","amnt_trade":"0.3990000000","user":"newminer7950","type":"sell","pub_date":"27  2021 . 16:58","id":6362341},"timestamp":1619531880000,"datetime":"2021-04-27T13:58:00.000Z","symbol":"BCH/UAH","side":"sell","price":24444.999,"amount":0.399},{"id":"6361009","info":{"amnt_base":"434.2844000000","order_id":176512176,"unixtime":1619505858,"price":"24398.0000000000","amnt_trade":"0.0178000000","user":"Alekskoll","type":"buy","pub_date":"27  2021 . 9:44","id":6361009},"timestamp":null,"symbol":"BCH/UAH","side":"buy","price":24398,"amount":0.0178},{"id":"6359199","info":{"amnt_base":"809.0449994003","order_id":176439394,"unixtime":1619461834,"price":"24398.0000000090","amnt_trade":"0.0331603000","user":"vadim22891","type":"buy","pub_date":"26  2021 . 21:30","id":6359199},"timestamp":1619461800000,"datetime":"2021-04-26T18:30:00.000Z","symbol":"BCH/UAH","side":"buy","price":24398.000000009,"amount":0.0331603}]}}